{"10/27/2015_CHI_CLE": {"date": "10/27/2015", "home": "Chicago Bulls", "visitor": "Cleveland Cavaliers", "shots_home": [{"x": "25.9 ft", "y": "5.07 ft", "QUARTER": 1, "TIME_REMAINING": "11:35.0", "PLAYER": "Nikola Miroti\u0107", "MAKE_MISS": "MISS", "VALUE": 2, "DISTANCE": "2 ft", "TEAM": "home", "HOME_SCORE": 0, "IMAGE": "https://d2cwpp38twqe55.cloudfront.net/req/202006192/images/players/mirotni01.jpg"}, {"x": "27.5 ft", "y": "4.08 ft", "QUARTER": 1, "TIME_REMAINING": "11:11.0", "PLAYER": "Derrick Rose", "MAKE_MISS": "MISS", "VALUE": 2, "DISTANCE": "3 ft", "TEAM": "home", "HOME_SCORE": 0, "IMAGE": "https://d2cwpp38twqe55.cloudfront.net/req/202006192/images/players/rosede01.jpg"}, {"x": "30.8 ft", "y": "20.7 ft", "QUARTER": 1, "TIME_REMAINING": "10:49.0", "PLAYER": "Pau Gasol", "MAKE_MISS": "MISS", "VALUE": 2, "DISTANCE": "19 ft", "TEAM": "home", "HOME_SCORE": 0, "IMAGE": "https://d2cwpp38twqe55.cloudfront.net/req/202006192/images/players/gasolpa01.jpg"}, {"x": "25.4 ft", "y": "3.78 ft", "QUARTER": 1, "TIME_REMAINING": "10:05.0", "PLAYER": "Nikola Miroti\u0107", "MAKE_MISS": "MISS", "VALUE": 2, "DISTANCE": "1 ft", "TEAM": "home", "HOME_SCORE": 0, "IMAGE": "https://d2cwpp38twqe55.cloudfront.net/req/202006192/images/players/mirotni01.jpg"}, {"x": "25.4 ft", "y": "3.78 ft", "QUARTER": 1, "TIME_REMAINING": "10:04.0", "PLAYER": "Nikola Miroti\u0107", "MAKE_MISS": "MAKE", "VALUE": 2, "DISTANCE": "1 ft", "TEAM": "home", "HOME_SCORE": 2, "IMAGE": "https://d2cwpp38twqe55.cloudfront.net/req/202006192/images/players/mirotni01.jpg"}, {"QUARTER": 1, "TIME_REMAINING": "10:04.0", "PLAYER": "Nikola Miroti\u0107", "IMAGE": "https://d2cwpp38twqe55.cloudfront.net/req/202006192/images/players/mirotni01.jpg", "TEAM": "home", "HOME_SCORE": 0, "VISITOR_SCORE": 6, "REBOUND": "Offensive"}, {"QUARTER": 1, "TIME_REMAINING": "9:46.0", "PLAYER": "Nikola Miroti\u0107", "IMAGE": "https://d2cwpp38twqe55.cloudfront.net/req/202006192/images/players/mirotni01.jpg", "TEAM": "home", "HOME_SCORE": 2, "VISITOR_SCORE": 6, "REBOUND": "Defensive"}, {"x": "26.5 ft", "y": "5.07 ft", "QUARTER": 1, "TIME_REMAINING": "9:38.0", "PLAYER": "Derrick Rose", "MAKE_MISS": "MAKE", "VALUE": 2, "DISTANCE": "3 ft", "TEAM": "home", "HOME_SCORE": 4, "IMAGE": "https://d2cwpp38twqe55.cloudfront.net/req/202006192/images/players/rosede01.jpg"}, {"x": "21.6 ft", "y": "4.28 ft", "QUARTER": 1, "TIME_REMAINING": "9:07.0", "PLAYER": "Derrick Rose", "MAKE_MISS": "MISS", "VALUE": 2, "DISTANCE": "2 ft", "TEAM": "home", "HOME_SCORE": 4, "IMAGE": "https://d2cwpp38twqe55.cloudfront.net/req/202006192/images/players/rosede01.jpg"}, {"x": "18.5 ft", "y": "22.7 ft", "QUARTER": 1, "TIME_REMAINING": "8:40.0", "PLAYER": "Jimmy Butler", "MAKE_MISS": "MISS", "VALUE": 2, "DISTANCE": "20 ft", "TEAM": "home", "HOME_SCORE": 4, "IMAGE": "https://d2cwpp38twqe55.cloudfront.net/req/202006192/images/players/butleji01.jpg"}, {"x": "24.0 ft", "y": "3.08 ft", "QUARTER": 1, "TIME_REMAINING": "8:14.0", "PLAYER": "Jimmy Butler", "MAKE_MISS": "MAKE", "VALUE": 2, "DISTANCE": "0 ft", "TEAM": "home", "HOME_SCORE": 6, "ASSIST": "Nikola Miroti\u0107", "IMAGE": "https://d2cwpp38twqe55.cloudfront.net/req/202006192/images/players/butleji01.jpg"}, {"x": "26.0 ft", "y": "4.77 ft", "QUARTER": 1, "TIME_REMAINING": "7:48.0", "PLAYER": "Derrick Rose", "MAKE_MISS": "MISS", "VALUE": 2, "DISTANCE": "2 ft", "TEAM": "home", "HOME_SCORE": 6, "IMAGE": "https://d2cwpp38twqe55.cloudfront.net/req/202006192/images/players/rosede01.jpg"}, {"x": "47.1 ft", "y": "1.39 ft", "QUARTER": 1, "TIME_REMAINING": "7:38.0", "PLAYER": "Derrick Rose", "MAKE_MISS": "MISS", "VALUE": 3, "DISTANCE": "23 ft", "TEAM": "home", "HOME_SCORE": 6, "IMAGE": "https://d2cwpp38twqe55.cloudfront.net/req/202006192/images/players/rosede01.jpg"}, {"x": "26.4 ft", "y": "3.18 ft", "QUARTER": 1, "TIME_REMAINING": "7:19.0", "PLAYER": "Jimmy Butler", "MAKE_MISS": "MISS", "VALUE": 2, "DISTANCE": "2 ft", "TEAM": "home", "HOME_SCORE": 6, "IMAGE": "https://d2cwpp38twqe55.cloudfront.net/req/202006192/images/players/butleji01.jpg"}, {"QUARTER": 1, "TIME_REMAINING": "6:46.0", "PLAYER": "Jimmy Butler", "IMAGE": "https://d2cwpp38twqe55.cloudfront.net/req/202006192/images/players/butleji01.jpg", "TEAM": "home", "HOME_SCORE": 6, "VISITOR_SCORE": 12, "REBOUND": "Defensive"}, {"x": "23.3 ft", "y": "27.5 ft", "QUARTER": 1, "TIME_REMAINING": "6:36.0", "PLAYER": "Nikola Miroti\u0107", "MAKE_MISS": "MAKE", "VALUE": 3, "DISTANCE": "24 ft", "TEAM": "home", "HOME_SCORE": 9, "ASSIST": "Jimmy Butler", "IMAGE": "https://d2cwpp38twqe55.cloudfront.net/req/202006192/images/players/mirotni01.jpg"}, {"x": "42.1 ft", "y": "24.1 ft", "QUARTER": 1, "TIME_REMAINING": "5:56.0", "PLAYER": "Nikola Miroti\u0107", "MAKE_MISS": "MAKE", "VALUE": 3, "DISTANCE": "28 ft", "TEAM": "home", "HOME_SCORE": 12, "IMAGE": "https://d2cwpp38twqe55.cloudfront.net/req/202006192/images/players/mirotni01.jpg"}, {"QUARTER": 1, "TIME_REMAINING": "5:31.0", "PLAYER": "Aaron Brooks", "IMAGE": "https://d2cwpp38twqe55.cloudfront.net/req/202006192/images/players/brookaa01.jpg", "TEAM": "home", "HOME_SCORE": 12, "VISITOR_SCORE": 15, "REBOUND": "Defensive"}, {"x": "4.10 ft", "y": "17.0 ft", "QUARTER": 1, "TIME_REMAINING": "5:11.0", "PLAYER": "E'Twaun Moore", "MAKE_MISS": "MISS", "VALUE": 3, "DISTANCE": "24 ft", "TEAM": "home", "HOME_SCORE": 12, "IMAGE": "https://image.shutterstock.com/image-illustration/3d-small-person-double-thumbs-260nw-92842738.jpg"}, {"QUARTER": 1, "TIME_REMAINING": "5:02.0", "PLAYER": "E'Twaun Moore", "IMAGE": "https://image.shutterstock.com/image-illustration/3d-small-person-double-thumbs-260nw-92842738.jpg", "TEAM": "home", "HOME_SCORE": 12, "VISITOR_SCORE": 15, "REBOUND": "Defensive"}, {"x": "24.0 ft", "y": "3.08 ft", "QUARTER": 1, "TIME_REMAINING": "4:56.0", "PLAYER": "Nikola Miroti\u0107", "MAKE_MISS": "MAKE", "VALUE": 2, "DISTANCE": "0 ft", "TEAM": "home", "HOME_SCORE": 14, "ASSIST": "E'Twaun Moore", "IMAGE": "https://d2cwpp38twqe55.cloudfront.net/req/202006192/images/players/mirotni01.jpg"}, {"x": "25.0 ft", "y": "15.0 ft", "QUARTER": 1, "TIME_REMAINING": "4:56.0", "PLAYER": "Nikola Miroti\u0107", "IMAGE": "https://d2cwpp38twqe55.cloudfront.net/req/202006192/images/players/mirotni01.jpg", "MAKE_MISS": "MAKE", "VALUE": 1, "DISTANCE": "15 ft", "TEAM": "home", "HOME_SCORE": 15, "VISITOR_SCORE": 15}, {"QUARTER": 1, "TIME_REMAINING": "4:35.0", "PLAYER": "Joakim Noah", "IMAGE": "https://d2cwpp38twqe55.cloudfront.net/req/202006192/images/players/noahjo01.jpg", "TEAM": "home", "HOME_SCORE": 15, "VISITOR_SCORE": 15, "REBOUND": "Defensive"}, {"x": "30.4 ft", "y": "5.07 ft", "QUARTER": 1, "TIME_REMAINING": "4:16.0", "PLAYER": "E'Twaun Moore", "MAKE_MISS": "MAKE", "VALUE": 2, "DISTANCE": "6 ft", "TEAM": "home", "HOME_SCORE": 17, "IMAGE": "https://image.shutterstock.com/image-illustration/3d-small-person-double-thumbs-260nw-92842738.jpg"}, {"QUARTER": 1, "TIME_REMAINING": "3:53.0", "PLAYER": "Joakim Noah", "IMAGE": "https://d2cwpp38twqe55.cloudfront.net/req/202006192/images/players/noahjo01.jpg", "TEAM": "home", "HOME_SCORE": 17, "VISITOR_SCORE": 15, "REBOUND": "Defensive"}, {"x": "9.5 ft", "y": "9.65 ft", "QUARTER": 1, "TIME_REMAINING": "3:35.0", "PLAYER": "Aaron Brooks", "MAKE_MISS": "MISS", "VALUE": 2, "DISTANCE": "15 ft", "TEAM": "home", "HOME_SCORE": 17, "IMAGE": "https://d2cwpp38twqe55.cloudfront.net/req/202006192/images/players/brookaa01.jpg"}, {"QUARTER": 1, "TIME_REMAINING": "3:19.0", "PLAYER": "Doug McDermott", "IMAGE": "https://d2cwpp38twqe55.cloudfront.net/req/202006192/images/players/mcderdo01.jpg", "TEAM": "home", "HOME_SCORE": 17, "VISITOR_SCORE": 15, "REBOUND": "Defensive"}, {"x": "38.5 ft", "y": "5.07 ft", "QUARTER": 1, "TIME_REMAINING": "3:08.0", "PLAYER": "Taj Gibson", "MAKE_MISS": "MISS", "VALUE": 2, "DISTANCE": "14 ft", "TEAM": "home", "HOME_SCORE": 17, "IMAGE": "https://d2cwpp38twqe55.cloudfront.net/req/202006192/images/players/gibsota01.jpg"}, {"QUARTER": 1, "TIME_REMAINING": "3:08.0", "PLAYER": "Joakim Noah", "IMAGE": "https://d2cwpp38twqe55.cloudfront.net/req/202006192/images/players/noahjo01.jpg", "TEAM": "home", "HOME_SCORE": 17, "VISITOR_SCORE": 15, "REBOUND": "Offensive"}, {"x": "23.3 ft", "y": "25.1 ft", "QUARTER": 1, "TIME_REMAINING": "2:56.0", "PLAYER": "Tony Snell", "MAKE_MISS": "MISS", "VALUE": 2, "DISTANCE": "22 ft", "TEAM": "home", "HOME_SCORE": 17, "IMAGE": "https://d2cwpp38twqe55.cloudfront.net/req/202006192/images/players/snellto01.jpg"}, {"x": "25.0 ft", "y": "15.0 ft", "QUARTER": 1, "TIME_REMAINING": "2:18.0", "PLAYER": "Taj Gibson", "IMAGE": "https://d2cwpp38twqe55.cloudfront.net/req/202006192/images/players/gibsota01.jpg", "MAKE_MISS": "MISS", "VALUE": 1, "DISTANCE": "15 ft", "TEAM": "home", "HOME_SCORE": 17, "VISITOR_SCORE": 15}, {"x": "25.0 ft", "y": "15.0 ft", "QUARTER": 1, "TIME_REMAINING": "2:18.0", "PLAYER": "Taj Gibson", "IMAGE": "https://d2cwpp38twqe55.cloudfront.net/req/202006192/images/players/gibsota01.jpg", "MAKE_MISS": "MAKE", "VALUE": 1, "DISTANCE": "15 ft", "TEAM": "home", "HOME_SCORE": 18, "VISITOR_SCORE": 15}, {"QUARTER": 1, "TIME_REMAINING": "1:59.0", "PLAYER": "Jimmy Butler", "IMAGE": "https://d2cwpp38twqe55.cloudfront.net/req/202006192/images/players/butleji01.jpg", "TEAM": "home", "HOME_SCORE": 18, "VISITOR_SCORE": 15, "REBOUND": "Defensive"}, {"x": "25.0 ft", "y": "15.0 ft", "QUARTER": 1, "TIME_REMAINING": "1:59.0", "PLAYER": "Jimmy Butler", "IMAGE": "https://d2cwpp38twqe55.cloudfront.net/req/202006192/images/players/butleji01.jpg", "MAKE_MISS": "MAKE", "VALUE": 1, "DISTANCE": "15 ft", "TEAM": "home", "HOME_SCORE": 19, "VISITOR_SCORE": 15}, {"x": "25.0 ft", "y": "15.0 ft", "QUARTER": 1, "TIME_REMAINING": "1:59.0", "PLAYER": "Jimmy Butler", "IMAGE": "https://d2cwpp38twqe55.cloudfront.net/req/202006192/images/players/butleji01.jpg", "MAKE_MISS": "MAKE", "VALUE": 1, "DISTANCE": "15 ft", "TEAM": "home", "HOME_SCORE": 20, "VISITOR_SCORE": 15}, {"QUARTER": 1, "TIME_REMAINING": "1:46.0", "PLAYER": "Jimmy Butler", "IMAGE": "https://d2cwpp38twqe55.cloudfront.net/req/202006192/images/players/butleji01.jpg", "TEAM": "home", "HOME_SCORE": 20, "VISITOR_SCORE": 15, "REBOUND": "Defensive"}, {"x": "12.8 ft", "y": "21.2 ft", "QUARTER": 1, "TIME_REMAINING": "1:29.0", "PLAYER": "Derrick Rose", "MAKE_MISS": "MISS", "VALUE": 2, "DISTANCE": "21 ft", "TEAM": "home", "HOME_SCORE": 20, "IMAGE": "https://d2cwpp38twqe55.cloudfront.net/req/202006192/images/players/rosede01.jpg"}, {"QUARTER": 1, "TIME_REMAINING": "1:29.0", "PLAYER": "Taj Gibson", "IMAGE": "https://d2cwpp38twqe55.cloudfront.net/req/202006192/images/players/gibsota01.jpg", "TEAM": "home", "HOME_SCORE": 20, "VISITOR_SCORE": 15, "REBOUND": "Offensive"}, {"x": "25.0 ft", "y": "15.0 ft", "QUARTER": 1, "TIME_REMAINING": "1:29.0", "PLAYER": "Taj Gibson", "IMAGE": "https://d2cwpp38twqe55.cloudfront.net/req/202006192/images/players/gibsota01.jpg", "MAKE_MISS": "MAKE", "VALUE": 1, "DISTANCE": "15 ft", "TEAM": "home", "HOME_SCORE": 21, "VISITOR_SCORE": 15}, {"x": "25.0 ft", "y": "15.0 ft", "QUARTER": 1, "TIME_REMAINING": "1:29.0", "PLAYER": "Taj Gibson", "IMAGE": "https://d2cwpp38twqe55.cloudfront.net/req/202006192/images/players/gibsota01.jpg", "MAKE_MISS": "MAKE", "VALUE": 1, "DISTANCE": "15 ft", "TEAM": "home", "HOME_SCORE": 22, "VISITOR_SCORE": 15}, {"x": "25.9 ft", "y": "3.68 ft", "QUARTER": 1, "TIME_REMAINING": "0:46.0", "PLAYER": "E'Twaun Moore", "MAKE_MISS": "MAKE", "VALUE": 2, "DISTANCE": "2 ft", "TEAM": "home", "HOME_SCORE": 24, "ASSIST": "Derrick Rose", "IMAGE": "https://image.shutterstock.com/image-illustration/3d-small-person-double-thumbs-260nw-92842738.jpg"}, {"QUARTER": 1, "TIME_REMAINING": "0:29.0", "PLAYER": "E'Twaun Moore", "IMAGE": "https://image.shutterstock.com/image-illustration/3d-small-person-double-thumbs-260nw-92842738.jpg", "TEAM": "home", "HOME_SCORE": 24, "VISITOR_SCORE": 17, "REBOUND": "Defensive"}, {"x": "24.0 ft", "y": "7.56 ft", "QUARTER": 1, "TIME_REMAINING": "0:11.0", "PLAYER": "Nikola Miroti\u0107", "MAKE_MISS": "MISS", "VALUE": 2, "DISTANCE": "4 ft", "TEAM": "home", "HOME_SCORE": 24, "IMAGE": "https://d2cwpp38twqe55.cloudfront.net/req/202006192/images/players/mirotni01.jpg"}, {"x": "4.9 ft", "y": "-0.0 ft", "QUARTER": 1, "TIME_REMAINING": "0:06.0", "PLAYER": "Jimmy Butler", "MAKE_MISS": "MAKE", "VALUE": 2, "DISTANCE": "19 ft", "TEAM": "home", "HOME_SCORE": 26, "IMAGE": "https://d2cwpp38twqe55.cloudfront.net/req/202006192/images/players/butleji01.jpg"}, {"QUARTER": 2, "TIME_REMAINING": "11:40.0", "PLAYER": "Taj Gibson", "IMAGE": "https://d2cwpp38twqe55.cloudfront.net/req/202006192/images/players/gibsota01.jpg", "TEAM": "home", "HOME_SCORE": 26, "VISITOR_SCORE": 17, "REBOUND": "Defensive"}, {"x": "9.70 ft", "y": "8.06 ft", "QUARTER": 2, "TIME_REMAINING": "11:25.0", "PLAYER": "Derrick Rose", "MAKE_MISS": "MAKE", "VALUE": 2, "DISTANCE": "15 ft", "TEAM": "home", "HOME_SCORE": 28, "IMAGE": "https://d2cwpp38twqe55.cloudfront.net/req/202006192/images/players/rosede01.jpg"}, {"x": "8.7 ft", "y": "5.07 ft", "QUARTER": 2, "TIME_REMAINING": "10:36.0", "PLAYER": "Tony Snell", "MAKE_MISS": "MAKE", "VALUE": 2, "DISTANCE": "15 ft", "TEAM": "home", "HOME_SCORE": 30, "IMAGE": "https://d2cwpp38twqe55.cloudfront.net/req/202006192/images/players/snellto01.jpg"}, {"x": "36.5 ft", "y": "23.2 ft", "QUARTER": 2, "TIME_REMAINING": "10:09.0", "PLAYER": "Jimmy Butler", "MAKE_MISS": "MISS", "VALUE": 3, "DISTANCE": "23 ft", "TEAM": "home", "HOME_SCORE": 30, "IMAGE": "https://d2cwpp38twqe55.cloudfront.net/req/202006192/images/players/butleji01.jpg"}, {"QUARTER": 2, "TIME_REMAINING": "10:05.0", "PLAYER": "Taj Gibson", "IMAGE": "https://d2cwpp38twqe55.cloudfront.net/req/202006192/images/players/gibsota01.jpg", "TEAM": "home", "HOME_SCORE": 30, "VISITOR_SCORE": 22, "REBOUND": "Defensive"}, {"x": "23.9 ft", "y": "5.37 ft", "QUARTER": 2, "TIME_REMAINING": "9:54.0", "PLAYER": "Derrick Rose", "MAKE_MISS": "MISS", "VALUE": 2, "DISTANCE": "2 ft", "TEAM": "home", "HOME_SCORE": 30, "IMAGE": "https://d2cwpp38twqe55.cloudfront.net/req/202006192/images/players/rosede01.jpg"}, {"QUARTER": 2, "TIME_REMAINING": "9:46.0", "PLAYER": "Taj Gibson", "IMAGE": "https://d2cwpp38twqe55.cloudfront.net/req/202006192/images/players/gibsota01.jpg", "TEAM": "home", "HOME_SCORE": 30, "VISITOR_SCORE": 22, "REBOUND": "Defensive"}, {"x": "22.0 ft", "y": "3.68 ft", "QUARTER": 2, "TIME_REMAINING": "9:42.0", "PLAYER": "Derrick Rose", "MAKE_MISS": "MISS", "VALUE": 2, "DISTANCE": "2 ft", "TEAM": "home", "HOME_SCORE": 30, "IMAGE": "https://d2cwpp38twqe55.cloudfront.net/req/202006192/images/players/rosede01.jpg"}, {"x": "23.1 ft", "y": "4.08 ft", "QUARTER": 2, "TIME_REMAINING": "9:41.0", "PLAYER": "Jimmy Butler", "MAKE_MISS": "MAKE", "VALUE": 2, "DISTANCE": "1 ft", "TEAM": "home", "HOME_SCORE": 32, "IMAGE": "https://d2cwpp38twqe55.cloudfront.net/req/202006192/images/players/butleji01.jpg"}, {"QUARTER": 2, "TIME_REMAINING": "9:41.0", "PLAYER": "Jimmy Butler", "IMAGE": "https://d2cwpp38twqe55.cloudfront.net/req/202006192/images/players/butleji01.jpg", "TEAM": "home", "HOME_SCORE": 30, "VISITOR_SCORE": 22, "REBOUND": "Offensive"}, {"QUARTER": 2, "TIME_REMAINING": "9:01.0", "PLAYER": "Taj Gibson", "IMAGE": "https://d2cwpp38twqe55.cloudfront.net/req/202006192/images/players/gibsota01.jpg", "TEAM": "home", "HOME_SCORE": 32, "VISITOR_SCORE": 22, "REBOUND": "Defensive"}, {"x": "12.6 ft", "y": "10.1 ft", "QUARTER": 2, "TIME_REMAINING": "8:46.0", "PLAYER": "Pau Gasol", "MAKE_MISS": "MISS", "VALUE": 2, "DISTANCE": "13 ft", "TEAM": "home", "HOME_SCORE": 32, "IMAGE": "https://d2cwpp38twqe55.cloudfront.net/req/202006192/images/players/gasolpa01.jpg"}, {"QUARTER": 2, "TIME_REMAINING": "8:24.0", "PLAYER": "E'Twaun Moore", "IMAGE": "https://image.shutterstock.com/image-illustration/3d-small-person-double-thumbs-260nw-92842738.jpg", "TEAM": "home", "HOME_SCORE": 32, "VISITOR_SCORE": 22, "REBOUND": "Defensive"}, {"x": "40.6 ft", "y": "11.1 ft", "QUARTER": 2, "TIME_REMAINING": "8:18.0", "PLAYER": "Jimmy Butler", "MAKE_MISS": "MISS", "VALUE": 2, "DISTANCE": "18 ft", "TEAM": "home", "HOME_SCORE": 32, "IMAGE": "https://d2cwpp38twqe55.cloudfront.net/req/202006192/images/players/butleji01.jpg"}, {"x": "28.5 ft", "y": "27.7 ft", "QUARTER": 2, "TIME_REMAINING": "7:57.0", "PLAYER": "Jimmy Butler", "MAKE_MISS": "MISS", "VALUE": 3, "DISTANCE": "25 ft", "TEAM": "home", "HOME_SCORE": 32, "IMAGE": "https://d2cwpp38twqe55.cloudfront.net/req/202006192/images/players/butleji01.jpg"}, {"x": "28.9 ft", "y": "5.57 ft", "QUARTER": 2, "TIME_REMAINING": "7:47.0", "PLAYER": "Aaron Brooks", "MAKE_MISS": "MAKE", "VALUE": 2, "DISTANCE": "5 ft", "TEAM": "home", "HOME_SCORE": 34, "IMAGE": "https://d2cwpp38twqe55.cloudfront.net/req/202006192/images/players/brookaa01.jpg"}, {"QUARTER": 2, "TIME_REMAINING": "7:25.0", "PLAYER": "Aaron Brooks", "IMAGE": "https://d2cwpp38twqe55.cloudfront.net/req/202006192/images/players/brookaa01.jpg", "TEAM": "home", "HOME_SCORE": 34, "VISITOR_SCORE": 23, "REBOUND": "Defensive"}, {"x": "35.4 ft", "y": "11.4 ft", "QUARTER": 2, "TIME_REMAINING": "6:40.0", "PLAYER": "Jimmy Butler", "MAKE_MISS": "MISS", "VALUE": 2, "DISTANCE": "14 ft", "TEAM": "home", "HOME_SCORE": 34, "IMAGE": "https://d2cwpp38twqe55.cloudfront.net/req/202006192/images/players/butleji01.jpg"}, {"QUARTER": 2, "TIME_REMAINING": "5:59.0", "PLAYER": "Tony Snell", "IMAGE": "https://d2cwpp38twqe55.cloudfront.net/req/202006192/images/players/snellto01.jpg", "TEAM": "home", "HOME_SCORE": 34, "VISITOR_SCORE": 25, "REBOUND": "Defensive"}, {"x": "23.4 ft", "y": "3.68 ft", "QUARTER": 2, "TIME_REMAINING": "5:03.0", "PLAYER": "Derrick Rose", "MAKE_MISS": "MAKE", "VALUE": 2, "DISTANCE": "0 ft", "TEAM": "home", "HOME_SCORE": 36, "IMAGE": "https://d2cwpp38twqe55.cloudfront.net/req/202006192/images/players/rosede01.jpg"}, {"QUARTER": 2, "TIME_REMAINING": "4:42.0", "PLAYER": "Pau Gasol", "IMAGE": "https://d2cwpp38twqe55.cloudfront.net/req/202006192/images/players/gasolpa01.jpg", "TEAM": "home", "HOME_SCORE": 36, "VISITOR_SCORE": 28, "REBOUND": "Defensive"}, {"x": "7.5 ft", "y": "21.7 ft", "QUARTER": 2, "TIME_REMAINING": "4:33.0", "PLAYER": "Tony Snell", "MAKE_MISS": "MISS", "VALUE": 3, "DISTANCE": "25 ft", "TEAM": "home", "HOME_SCORE": 36, "IMAGE": "https://d2cwpp38twqe55.cloudfront.net/req/202006192/images/players/snellto01.jpg"}, {"x": "6.4 ft", "y": "21.7 ft", "QUARTER": 2, "TIME_REMAINING": "4:14.0", "PLAYER": "Tony Snell", "MAKE_MISS": "MISS", "VALUE": 3, "DISTANCE": "25 ft", "TEAM": "home", "HOME_SCORE": 36, "IMAGE": "https://d2cwpp38twqe55.cloudfront.net/req/202006192/images/players/snellto01.jpg"}, {"QUARTER": 2, "TIME_REMAINING": "3:57.0", "PLAYER": "Joakim Noah", "IMAGE": "https://d2cwpp38twqe55.cloudfront.net/req/202006192/images/players/noahjo01.jpg", "TEAM": "home", "HOME_SCORE": 36, "VISITOR_SCORE": 30, "REBOUND": "Defensive"}, {"x": "25.2 ft", "y": "5.57 ft", "QUARTER": 2, "TIME_REMAINING": "3:29.0", "PLAYER": "Derrick Rose", "MAKE_MISS": "MISS", "VALUE": 2, "DISTANCE": "2 ft", "TEAM": "home", "HOME_SCORE": 36, "IMAGE": "https://d2cwpp38twqe55.cloudfront.net/req/202006192/images/players/rosede01.jpg"}, {"QUARTER": 2, "TIME_REMAINING": "3:29.0", "PLAYER": "Joakim Noah", "IMAGE": "https://d2cwpp38twqe55.cloudfront.net/req/202006192/images/players/noahjo01.jpg", "TEAM": "home", "HOME_SCORE": 36, "VISITOR_SCORE": 32, "REBOUND": "Offensive"}, {"x": "33.6 ft", "y": "26.0 ft", "QUARTER": 2, "TIME_REMAINING": "3:20.0", "PLAYER": "Tony Snell", "MAKE_MISS": "MAKE", "VALUE": 3, "DISTANCE": "25 ft", "TEAM": "home", "HOME_SCORE": 39, "ASSIST": "Joakim Noah", "IMAGE": "https://d2cwpp38twqe55.cloudfront.net/req/202006192/images/players/snellto01.jpg"}, {"QUARTER": 2, "TIME_REMAINING": "3:02.0", "PLAYER": "Doug McDermott", "IMAGE": "https://d2cwpp38twqe55.cloudfront.net/req/202006192/images/players/mcderdo01.jpg", "TEAM": "home", "HOME_SCORE": 39, "VISITOR_SCORE": 32, "REBOUND": "Defensive"}, {"x": "24.6 ft", "y": "8.06 ft", "QUARTER": 2, "TIME_REMAINING": "2:46.0", "PLAYER": "Derrick Rose", "MAKE_MISS": "MISS", "VALUE": 2, "DISTANCE": "5 ft", "TEAM": "home", "HOME_SCORE": 39, "IMAGE": "https://d2cwpp38twqe55.cloudfront.net/req/202006192/images/players/rosede01.jpg"}, {"x": "11.6 ft", "y": "21.2 ft", "QUARTER": 2, "TIME_REMAINING": "2:16.0", "PLAYER": "Doug McDermott", "MAKE_MISS": "MAKE", "VALUE": 2, "DISTANCE": "22 ft", "TEAM": "home", "HOME_SCORE": 41, "IMAGE": "https://d2cwpp38twqe55.cloudfront.net/req/202006192/images/players/mcderdo01.jpg"}, {"QUARTER": 2, "TIME_REMAINING": "1:54.0", "PLAYER": "Doug McDermott", "IMAGE": "https://d2cwpp38twqe55.cloudfront.net/req/202006192/images/players/mcderdo01.jpg", "TEAM": "home", "HOME_SCORE": 41, "VISITOR_SCORE": 35, "REBOUND": "Defensive"}, {"x": "25.0 ft", "y": "15.0 ft", "QUARTER": 2, "TIME_REMAINING": "1:51.0", "PLAYER": "Joakim Noah", "IMAGE": "https://d2cwpp38twqe55.cloudfront.net/req/202006192/images/players/noahjo01.jpg", "MAKE_MISS": "MISS", "VALUE": 1, "DISTANCE": "15 ft", "TEAM": "home", "HOME_SCORE": 41, "VISITOR_SCORE": 35}, {"x": "25.0 ft", "y": "15.0 ft", "QUARTER": 2, "TIME_REMAINING": "1:51.0", "PLAYER": "Joakim Noah", "IMAGE": "https://d2cwpp38twqe55.cloudfront.net/req/202006192/images/players/noahjo01.jpg", "MAKE_MISS": "MISS", "VALUE": 1, "DISTANCE": "15 ft", "TEAM": "home", "HOME_SCORE": 41, "VISITOR_SCORE": 35}, {"QUARTER": 2, "TIME_REMAINING": "1:49.0", "PLAYER": "Taj Gibson", "IMAGE": "https://d2cwpp38twqe55.cloudfront.net/req/202006192/images/players/gibsota01.jpg", "TEAM": "home", "HOME_SCORE": 41, "VISITOR_SCORE": 35, "REBOUND": "Offensive"}, {"x": "7.1 ft", "y": "21.4 ft", "QUARTER": 2, "TIME_REMAINING": "1:16.0", "PLAYER": "Doug McDermott", "MAKE_MISS": "MAKE", "VALUE": 3, "DISTANCE": "25 ft", "TEAM": "home", "HOME_SCORE": 44, "ASSIST": "Jimmy Butler", "IMAGE": "https://d2cwpp38twqe55.cloudfront.net/req/202006192/images/players/mcderdo01.jpg"}, {"QUARTER": 2, "TIME_REMAINING": "1:01.0", "PLAYER": "Joakim Noah", "IMAGE": "https://d2cwpp38twqe55.cloudfront.net/req/202006192/images/players/noahjo01.jpg", "TEAM": "home", "HOME_SCORE": 44, "VISITOR_SCORE": 37, "REBOUND": "Defensive"}, {"x": "10.8 ft", "y": "2.48 ft", "QUARTER": 2, "TIME_REMAINING": "0:53.0", "PLAYER": "Taj Gibson", "MAKE_MISS": "MISS", "VALUE": 2, "DISTANCE": "13 ft", "TEAM": "home", "HOME_SCORE": 44, "IMAGE": "https://d2cwpp38twqe55.cloudfront.net/req/202006192/images/players/gibsota01.jpg"}, {"QUARTER": 2, "TIME_REMAINING": "0:34.0", "PLAYER": "Taj Gibson", "IMAGE": "https://d2cwpp38twqe55.cloudfront.net/req/202006192/images/players/gibsota01.jpg", "TEAM": "home", "HOME_SCORE": 44, "VISITOR_SCORE": 37, "REBOUND": "Defensive"}, {"x": "7.39 ft", "y": "2.38 ft", "QUARTER": 2, "TIME_REMAINING": "0:24.0", "PLAYER": "Doug McDermott", "MAKE_MISS": "MAKE", "VALUE": 2, "DISTANCE": "16 ft", "TEAM": "home", "HOME_SCORE": 46, "ASSIST": "Joakim Noah", "IMAGE": "https://d2cwpp38twqe55.cloudfront.net/req/202006192/images/players/mcderdo01.jpg"}, {"x": "23.1 ft", "y": "8.56 ft", "QUARTER": 3, "TIME_REMAINING": "11:02.0", "PLAYER": "Tony Snell", "MAKE_MISS": "MAKE", "VALUE": 2, "DISTANCE": "5 ft", "TEAM": "home", "HOME_SCORE": 48, "IMAGE": "https://d2cwpp38twqe55.cloudfront.net/req/202006192/images/players/snellto01.jpg"}, {"x": "19.5 ft", "y": "28.5 ft", "QUARTER": 3, "TIME_REMAINING": "10:47.0", "PLAYER": "Nikola Miroti\u0107", "MAKE_MISS": "MAKE", "VALUE": 3, "DISTANCE": "26 ft", "TEAM": "home", "HOME_SCORE": 51, "ASSIST": "Derrick Rose", "IMAGE": "https://d2cwpp38twqe55.cloudfront.net/req/202006192/images/players/mirotni01.jpg"}, {"x": "22.6 ft", "y": "3.18 ft", "QUARTER": 3, "TIME_REMAINING": "10:12.0", "PLAYER": "Derrick Rose", "MAKE_MISS": "MAKE", "VALUE": 2, "DISTANCE": "1 ft", "TEAM": "home", "HOME_SCORE": 53, "IMAGE": "https://d2cwpp38twqe55.cloudfront.net/req/202006192/images/players/rosede01.jpg"}, {"x": "25.0 ft", "y": "15.0 ft", "QUARTER": 3, "TIME_REMAINING": "10:12.0", "PLAYER": "Derrick Rose", "IMAGE": "https://d2cwpp38twqe55.cloudfront.net/req/202006192/images/players/rosede01.jpg", "MAKE_MISS": "MISS", "VALUE": 1, "DISTANCE": "15 ft", "TEAM": "home", "HOME_SCORE": 53, "VISITOR_SCORE": 46}, {"x": "38.8 ft", "y": "10.4 ft", "QUARTER": 3, "TIME_REMAINING": "9:37.0", "PLAYER": "Pau Gasol", "MAKE_MISS": "MAKE", "VALUE": 2, "DISTANCE": "16 ft", "TEAM": "home", "HOME_SCORE": 55, "ASSIST": "Derrick Rose", "IMAGE": "https://d2cwpp38twqe55.cloudfront.net/req/202006192/images/players/gasolpa01.jpg"}, {"QUARTER": 3, "TIME_REMAINING": "9:16.0", "PLAYER": "Nikola Miroti\u0107", "IMAGE": "https://d2cwpp38twqe55.cloudfront.net/req/202006192/images/players/mirotni01.jpg", "TEAM": "home", "HOME_SCORE": 55, "VISITOR_SCORE": 48, "REBOUND": "Defensive"}, {"x": "7.1 ft", "y": "20.9 ft", "QUARTER": 3, "TIME_REMAINING": "9:03.0", "PLAYER": "Derrick Rose", "MAKE_MISS": "MISS", "VALUE": 3, "DISTANCE": "24 ft", "TEAM": "home", "HOME_SCORE": 55, "IMAGE": "https://d2cwpp38twqe55.cloudfront.net/req/202006192/images/players/rosede01.jpg"}, {"QUARTER": 3, "TIME_REMAINING": "8:53.0", "PLAYER": "Nikola Miroti\u0107", "IMAGE": "https://d2cwpp38twqe55.cloudfront.net/req/202006192/images/players/mirotni01.jpg", "TEAM": "home", "HOME_SCORE": 55, "VISITOR_SCORE": 48, "REBOUND": "Defensive"}, {"x": "17.5 ft", "y": "3.18 ft", "QUARTER": 3, "TIME_REMAINING": "8:45.0", "PLAYER": "Derrick Rose", "MAKE_MISS": "MAKE", "VALUE": 2, "DISTANCE": "6 ft", "TEAM": "home", "HOME_SCORE": 57, "IMAGE": "https://d2cwpp38twqe55.cloudfront.net/req/202006192/images/players/rosede01.jpg"}, {"x": "25.0 ft", "y": "15.0 ft", "QUARTER": 3, "TIME_REMAINING": "8:45.0", "PLAYER": "Derrick Rose", "IMAGE": "https://d2cwpp38twqe55.cloudfront.net/req/202006192/images/players/rosede01.jpg", "MAKE_MISS": "MAKE", "VALUE": 1, "DISTANCE": "15 ft", "TEAM": "home", "HOME_SCORE": 58, "VISITOR_SCORE": 48}, {"x": "14.2 ft", "y": "26.2 ft", "QUARTER": 3, "TIME_REMAINING": "8:27.0", "PLAYER": "Tony Snell", "MAKE_MISS": "MAKE", "VALUE": 3, "DISTANCE": "25 ft", "TEAM": "home", "HOME_SCORE": 61, "ASSIST": "Derrick Rose", "IMAGE": "https://d2cwpp38twqe55.cloudfront.net/req/202006192/images/players/snellto01.jpg"}, {"x": "35.6 ft", "y": "24.2 ft", "QUARTER": 3, "TIME_REMAINING": "7:50.0", "PLAYER": "Tony Snell", "MAKE_MISS": "MISS", "VALUE": 3, "DISTANCE": "24 ft", "TEAM": "home", "HOME_SCORE": 61, "IMAGE": "https://d2cwpp38twqe55.cloudfront.net/req/202006192/images/players/snellto01.jpg"}, {"QUARTER": 3, "TIME_REMAINING": "7:41.0", "PLAYER": "Nikola Miroti\u0107", "IMAGE": "https://d2cwpp38twqe55.cloudfront.net/req/202006192/images/players/mirotni01.jpg", "TEAM": "home", "HOME_SCORE": 61, "VISITOR_SCORE": 50, "REBOUND": "Defensive"}, {"x": "23.3 ft", "y": "20.3 ft", "QUARTER": 3, "TIME_REMAINING": "7:27.0", "PLAYER": "Pau Gasol", "MAKE_MISS": "MISS", "VALUE": 2, "DISTANCE": "17 ft", "TEAM": "home", "HOME_SCORE": 61, "IMAGE": "https://d2cwpp38twqe55.cloudfront.net/req/202006192/images/players/gasolpa01.jpg"}, {"x": "33.4 ft", "y": "5.57 ft", "QUARTER": 3, "TIME_REMAINING": "6:46.0", "PLAYER": "Tony Snell", "MAKE_MISS": "MISS", "VALUE": 2, "DISTANCE": "9 ft", "TEAM": "home", "HOME_SCORE": 61, "IMAGE": "https://d2cwpp38twqe55.cloudfront.net/req/202006192/images/players/snellto01.jpg"}, {"x": "22.9 ft", "y": "10.4 ft", "QUARTER": 3, "TIME_REMAINING": "6:18.0", "PLAYER": "Derrick Rose", "MAKE_MISS": "MAKE", "VALUE": 2, "DISTANCE": "7 ft", "TEAM": "home", "HOME_SCORE": 63, "IMAGE": "https://d2cwpp38twqe55.cloudfront.net/req/202006192/images/players/rosede01.jpg"}, {"QUARTER": 3, "TIME_REMAINING": "6:00.0", "PLAYER": "Derrick Rose", "IMAGE": "https://d2cwpp38twqe55.cloudfront.net/req/202006192/images/players/rosede01.jpg", "TEAM": "home", "HOME_SCORE": 63, "VISITOR_SCORE": 52, "REBOUND": "Defensive"}, {"x": "25.7 ft", "y": "10.4 ft", "QUARTER": 3, "TIME_REMAINING": "5:50.0", "PLAYER": "Derrick Rose", "MAKE_MISS": "MISS", "VALUE": 2, "DISTANCE": "7 ft", "TEAM": "home", "HOME_SCORE": 63, "IMAGE": "https://d2cwpp38twqe55.cloudfront.net/req/202006192/images/players/rosede01.jpg"}, {"x": "38.0 ft", "y": "4.77 ft", "QUARTER": 3, "TIME_REMAINING": "5:24.0", "PLAYER": "Jimmy Butler", "MAKE_MISS": "MISS", "VALUE": 2, "DISTANCE": "14 ft", "TEAM": "home", "HOME_SCORE": 63, "IMAGE": "https://d2cwpp38twqe55.cloudfront.net/req/202006192/images/players/butleji01.jpg"}, {"x": "18.8 ft", "y": "10.4 ft", "QUARTER": 3, "TIME_REMAINING": "5:19.0", "PLAYER": "Pau Gasol", "MAKE_MISS": "MISS", "VALUE": 2, "DISTANCE": "9 ft", "TEAM": "home", "HOME_SCORE": 63, "IMAGE": "https://d2cwpp38twqe55.cloudfront.net/req/202006192/images/players/gasolpa01.jpg"}, {"QUARTER": 3, "TIME_REMAINING": "5:06.0", "PLAYER": "Tony Snell", "IMAGE": "https://d2cwpp38twqe55.cloudfront.net/req/202006192/images/players/snellto01.jpg", "TEAM": "home", "HOME_SCORE": 63, "VISITOR_SCORE": 55, "REBOUND": "Defensive"}, {"x": "35.4 ft", "y": "2.38 ft", "QUARTER": 3, "TIME_REMAINING": "4:59.0", "PLAYER": "Aaron Brooks", "MAKE_MISS": "MAKE", "VALUE": 2, "DISTANCE": "11 ft", "TEAM": "home", "HOME_SCORE": 65, "IMAGE": "https://d2cwpp38twqe55.cloudfront.net/req/202006192/images/players/brookaa01.jpg"}, {"QUARTER": 3, "TIME_REMAINING": "4:43.0", "PLAYER": "Taj Gibson", "IMAGE": "https://d2cwpp38twqe55.cloudfront.net/req/202006192/images/players/gibsota01.jpg", "TEAM": "home", "HOME_SCORE": 65, "VISITOR_SCORE": 55, "REBOUND": "Defensive"}, {"x": "28.7 ft", "y": "18.8 ft", "QUARTER": 3, "TIME_REMAINING": "4:09.0", "PLAYER": "Aaron Brooks", "MAKE_MISS": "MAKE", "VALUE": 2, "DISTANCE": "16 ft", "TEAM": "home", "HOME_SCORE": 67, "IMAGE": "https://d2cwpp38twqe55.cloudfront.net/req/202006192/images/players/brookaa01.jpg"}, {"QUARTER": 3, "TIME_REMAINING": "3:45.0", "PLAYER": "Taj Gibson", "IMAGE": "https://d2cwpp38twqe55.cloudfront.net/req/202006192/images/players/gibsota01.jpg", "TEAM": "home", "HOME_SCORE": 67, "VISITOR_SCORE": 57, "REBOUND": "Defensive"}, {"x": "26.7 ft", "y": "21.9 ft", "QUARTER": 3, "TIME_REMAINING": "3:34.0", "PLAYER": "Aaron Brooks", "MAKE_MISS": "MISS", "VALUE": 2, "DISTANCE": "19 ft", "TEAM": "home", "HOME_SCORE": 67, "IMAGE": "https://d2cwpp38twqe55.cloudfront.net/req/202006192/images/players/brookaa01.jpg"}, {"QUARTER": 3, "TIME_REMAINING": "3:23.0", "PLAYER": "Joakim Noah", "IMAGE": "https://d2cwpp38twqe55.cloudfront.net/req/202006192/images/players/noahjo01.jpg", "TEAM": "home", "HOME_SCORE": 67, "VISITOR_SCORE": 57, "REBOUND": "Defensive"}, {"x": "28.1 ft", "y": "9.65 ft", "QUARTER": 3, "TIME_REMAINING": "3:14.0", "PLAYER": "E'Twaun Moore", "MAKE_MISS": "MAKE", "VALUE": 2, "DISTANCE": "7 ft", "TEAM": "home", "HOME_SCORE": 69, "IMAGE": "https://image.shutterstock.com/image-illustration/3d-small-person-double-thumbs-260nw-92842738.jpg"}, {"x": "23.4 ft", "y": "18.5 ft", "QUARTER": 3, "TIME_REMAINING": "2:29.0", "PLAYER": "E'Twaun Moore", "MAKE_MISS": "MAKE", "VALUE": 2, "DISTANCE": "15 ft", "TEAM": "home", "HOME_SCORE": 71, "IMAGE": "https://image.shutterstock.com/image-illustration/3d-small-person-double-thumbs-260nw-92842738.jpg"}, {"x": "30.3 ft", "y": "9.06 ft", "QUARTER": 3, "TIME_REMAINING": "1:13.0", "PLAYER": "Aaron Brooks", "MAKE_MISS": "MISS", "VALUE": 2, "DISTANCE": "8 ft", "TEAM": "home", "HOME_SCORE": 71, "IMAGE": "https://d2cwpp38twqe55.cloudfront.net/req/202006192/images/players/brookaa01.jpg"}, {"QUARTER": 3, "TIME_REMAINING": "1:05.0", "PLAYER": "Joakim Noah", "IMAGE": "https://d2cwpp38twqe55.cloudfront.net/req/202006192/images/players/noahjo01.jpg", "TEAM": "home", "HOME_SCORE": 71, "VISITOR_SCORE": 64, "REBOUND": "Defensive"}, {"x": "10.2 ft", "y": "3.78 ft", "QUARTER": 3, "TIME_REMAINING": "0:53.0", "PLAYER": "Aaron Brooks", "MAKE_MISS": "MISS", "VALUE": 2, "DISTANCE": "13 ft", "TEAM": "home", "HOME_SCORE": 71, "IMAGE": "https://d2cwpp38twqe55.cloudfront.net/req/202006192/images/players/brookaa01.jpg"}, {"x": "19.3 ft", "y": "4.58 ft", "QUARTER": 3, "TIME_REMAINING": "0:33.0", "PLAYER": "E'Twaun Moore", "MAKE_MISS": "MISS", "VALUE": 2, "DISTANCE": "4 ft", "TEAM": "home", "HOME_SCORE": 71, "IMAGE": "https://image.shutterstock.com/image-illustration/3d-small-person-double-thumbs-260nw-92842738.jpg"}, {"x": "40.4 ft", "y": "2.88 ft", "QUARTER": 4, "TIME_REMAINING": "11:36.0", "PLAYER": "E'Twaun Moore", "MAKE_MISS": "MISS", "VALUE": 2, "DISTANCE": "16 ft", "TEAM": "home", "HOME_SCORE": 71, "IMAGE": "https://image.shutterstock.com/image-illustration/3d-small-person-double-thumbs-260nw-92842738.jpg"}, {"x": "-0.3 ft", "y": "7.26 ft", "QUARTER": 4, "TIME_REMAINING": "11:03.0", "PLAYER": "Aaron Brooks", "MAKE_MISS": "MISS", "VALUE": 3, "DISTANCE": "24 ft", "TEAM": "home", "HOME_SCORE": 71, "IMAGE": "https://d2cwpp38twqe55.cloudfront.net/req/202006192/images/players/brookaa01.jpg"}, {"QUARTER": 4, "TIME_REMAINING": "10:53.0", "PLAYER": "Taj Gibson", "IMAGE": "https://d2cwpp38twqe55.cloudfront.net/req/202006192/images/players/gibsota01.jpg", "TEAM": "home", "HOME_SCORE": 71, "VISITOR_SCORE": 71, "REBOUND": "Defensive"}, {"x": "12.3 ft", "y": "13.4 ft", "QUARTER": 4, "TIME_REMAINING": "10:44.0", "PLAYER": "Aaron Brooks", "MAKE_MISS": "MISS", "VALUE": 2, "DISTANCE": "15 ft", "TEAM": "home", "HOME_SCORE": 71, "IMAGE": "https://d2cwpp38twqe55.cloudfront.net/req/202006192/images/players/brookaa01.jpg"}, {"QUARTER": 4, "TIME_REMAINING": "10:29.0", "PLAYER": "Joakim Noah", "IMAGE": "https://d2cwpp38twqe55.cloudfront.net/req/202006192/images/players/noahjo01.jpg", "TEAM": "home", "HOME_SCORE": 71, "VISITOR_SCORE": 71, "REBOUND": "Defensive"}, {"x": "30.0 ft", "y": "26.5 ft", "QUARTER": 4, "TIME_REMAINING": "10:23.0", "PLAYER": "E'Twaun Moore", "MAKE_MISS": "MAKE", "VALUE": 3, "DISTANCE": "24 ft", "TEAM": "home", "HOME_SCORE": 74, "ASSIST": "Joakim Noah", "IMAGE": "https://image.shutterstock.com/image-illustration/3d-small-person-double-thumbs-260nw-92842738.jpg"}, {"QUARTER": 4, "TIME_REMAINING": "10:00.0", "PLAYER": "Doug McDermott", "IMAGE": "https://d2cwpp38twqe55.cloudfront.net/req/202006192/images/players/mcderdo01.jpg", "TEAM": "home", "HOME_SCORE": 74, "VISITOR_SCORE": 71, "REBOUND": "Defensive"}, {"x": "25.0 ft", "y": "15.0 ft", "QUARTER": 4, "TIME_REMAINING": "9:53.0", "PLAYER": "Doug McDermott", "IMAGE": "https://d2cwpp38twqe55.cloudfront.net/req/202006192/images/players/mcderdo01.jpg", "MAKE_MISS": "MAKE", "VALUE": 1, "DISTANCE": "15 ft", "TEAM": "home", "HOME_SCORE": 75, "VISITOR_SCORE": 71}, {"x": "25.0 ft", "y": "15.0 ft", "QUARTER": 4, "TIME_REMAINING": "9:53.0", "PLAYER": "Doug McDermott", "IMAGE": "https://d2cwpp38twqe55.cloudfront.net/req/202006192/images/players/mcderdo01.jpg", "MAKE_MISS": "MISS", "VALUE": 1, "DISTANCE": "15 ft", "TEAM": "home", "HOME_SCORE": 75, "VISITOR_SCORE": 71}, {"x": "30.9 ft", "y": "15.3 ft", "QUARTER": 4, "TIME_REMAINING": "9:18.0", "PLAYER": "Taj Gibson", "MAKE_MISS": "MAKE", "VALUE": 2, "DISTANCE": "14 ft", "TEAM": "home", "HOME_SCORE": 77, "ASSIST": "Joakim Noah", "IMAGE": "https://d2cwpp38twqe55.cloudfront.net/req/202006192/images/players/gibsota01.jpg"}, {"x": "30.0 ft", "y": "23.2 ft", "QUARTER": 4, "TIME_REMAINING": "8:40.0", "PLAYER": "Pau Gasol", "MAKE_MISS": "MISS", "VALUE": 2, "DISTANCE": "21 ft", "TEAM": "home", "HOME_SCORE": 77, "IMAGE": "https://d2cwpp38twqe55.cloudfront.net/req/202006192/images/players/gasolpa01.jpg"}, {"x": "42.1 ft", "y": "20.4 ft", "QUARTER": 4, "TIME_REMAINING": "8:11.0", "PLAYER": "Pau Gasol", "MAKE_MISS": "MISS", "VALUE": 3, "DISTANCE": "25 ft", "TEAM": "home", "HOME_SCORE": 77, "IMAGE": "https://d2cwpp38twqe55.cloudfront.net/req/202006192/images/players/gasolpa01.jpg"}, {"x": "3.9 ft", "y": "3.18 ft", "QUARTER": 4, "TIME_REMAINING": "7:48.0", "PLAYER": "Jimmy Butler", "MAKE_MISS": "MISS", "VALUE": 2, "DISTANCE": "20 ft", "TEAM": "home", "HOME_SCORE": 77, "IMAGE": "https://d2cwpp38twqe55.cloudfront.net/req/202006192/images/players/butleji01.jpg"}, {"QUARTER": 4, "TIME_REMAINING": "7:33.0", "PLAYER": "Pau Gasol", "IMAGE": "https://d2cwpp38twqe55.cloudfront.net/req/202006192/images/players/gasolpa01.jpg", "TEAM": "home", "HOME_SCORE": 77, "VISITOR_SCORE": 75, "REBOUND": "Defensive"}, {"x": "25.0 ft", "y": "15.0 ft", "QUARTER": 4, "TIME_REMAINING": "7:27.0", "PLAYER": "Derrick Rose", "IMAGE": "https://d2cwpp38twqe55.cloudfront.net/req/202006192/images/players/rosede01.jpg", "MAKE_MISS": "MISS", "VALUE": 1, "DISTANCE": "15 ft", "TEAM": "home", "HOME_SCORE": 77, "VISITOR_SCORE": 75}, {"x": "25.0 ft", "y": "15.0 ft", "QUARTER": 4, "TIME_REMAINING": "7:27.0", "PLAYER": "Derrick Rose", "IMAGE": "https://d2cwpp38twqe55.cloudfront.net/req/202006192/images/players/rosede01.jpg", "MAKE_MISS": "MAKE", "VALUE": 1, "DISTANCE": "15 ft", "TEAM": "home", "HOME_SCORE": 78, "VISITOR_SCORE": 75}, {"x": "5.89 ft", "y": "12.9 ft", "QUARTER": 4, "TIME_REMAINING": "6:58.0", "PLAYER": "Jimmy Butler", "MAKE_MISS": "MAKE", "VALUE": 2, "DISTANCE": "20 ft", "TEAM": "home", "HOME_SCORE": 80, "IMAGE": "https://d2cwpp38twqe55.cloudfront.net/req/202006192/images/players/butleji01.jpg"}, {"x": "13.9 ft", "y": "13.9 ft", "QUARTER": 4, "TIME_REMAINING": "6:20.0", "PLAYER": "Derrick Rose", "MAKE_MISS": "MAKE", "VALUE": 2, "DISTANCE": "14 ft", "TEAM": "home", "HOME_SCORE": 82, "IMAGE": "https://d2cwpp38twqe55.cloudfront.net/req/202006192/images/players/rosede01.jpg"}, {"x": "25.0 ft", "y": "5.07 ft", "QUARTER": 4, "TIME_REMAINING": "5:50.0", "PLAYER": "Derrick Rose", "MAKE_MISS": "MISS", "VALUE": 2, "DISTANCE": "2 ft", "TEAM": "home", "HOME_SCORE": 82, "IMAGE": "https://d2cwpp38twqe55.cloudfront.net/req/202006192/images/players/rosede01.jpg"}, {"x": "11.5 ft", "y": "2.38 ft", "QUARTER": 4, "TIME_REMAINING": "5:18.0", "PLAYER": "Nikola Miroti\u0107", "MAKE_MISS": "MAKE", "VALUE": 2, "DISTANCE": "12 ft", "TEAM": "home", "HOME_SCORE": 84, "IMAGE": "https://d2cwpp38twqe55.cloudfront.net/req/202006192/images/players/mirotni01.jpg"}, {"x": "25.0 ft", "y": "15.0 ft", "QUARTER": 4, "TIME_REMAINING": "5:18.0", "PLAYER": "Nikola Miroti\u0107", "IMAGE": "https://d2cwpp38twqe55.cloudfront.net/req/202006192/images/players/mirotni01.jpg", "MAKE_MISS": "MAKE", "VALUE": 1, "DISTANCE": "15 ft", "TEAM": "home", "HOME_SCORE": 85, "VISITOR_SCORE": 83}, {"QUARTER": 4, "TIME_REMAINING": "5:05.0", "PLAYER": "Nikola Miroti\u0107", "IMAGE": "https://d2cwpp38twqe55.cloudfront.net/req/202006192/images/players/mirotni01.jpg", "TEAM": "home", "HOME_SCORE": 85, "VISITOR_SCORE": 83, "REBOUND": "Defensive"}, {"x": "25.0 ft", "y": "15.0 ft", "QUARTER": 4, "TIME_REMAINING": "4:58.0", "PLAYER": "Nikola Miroti\u0107", "IMAGE": "https://d2cwpp38twqe55.cloudfront.net/req/202006192/images/players/mirotni01.jpg", "MAKE_MISS": "MAKE", "VALUE": 1, "DISTANCE": "15 ft", "TEAM": "home", "HOME_SCORE": 87, "VISITOR_SCORE": 83}, {"x": "25.0 ft", "y": "15.0 ft", "QUARTER": 4, "TIME_REMAINING": "4:58.0", "PLAYER": "Nikola Miroti\u0107", "IMAGE": "https://d2cwpp38twqe55.cloudfront.net/req/202006192/images/players/mirotni01.jpg", "MAKE_MISS": "MAKE", "VALUE": 1, "DISTANCE": "15 ft", "TEAM": "home", "HOME_SCORE": 88, "VISITOR_SCORE": 83}, {"x": "24.0 ft", "y": "3.08 ft", "QUARTER": 4, "TIME_REMAINING": "4:24.0", "PLAYER": "Jimmy Butler", "MAKE_MISS": "MAKE", "VALUE": 2, "DISTANCE": "0 ft", "TEAM": "home", "HOME_SCORE": 90, "IMAGE": "https://d2cwpp38twqe55.cloudfront.net/req/202006192/images/players/butleji01.jpg"}, {"QUARTER": 4, "TIME_REMAINING": "3:58.0", "PLAYER": "Nikola Miroti\u0107", "IMAGE": "https://d2cwpp38twqe55.cloudfront.net/req/202006192/images/players/mirotni01.jpg", "TEAM": "home", "HOME_SCORE": 90, "VISITOR_SCORE": 85, "REBOUND": "Defensive"}, {"x": "25.0 ft", "y": "15.0 ft", "QUARTER": 4, "TIME_REMAINING": "3:53.0", "PLAYER": "Tony Snell", "IMAGE": "https://d2cwpp38twqe55.cloudfront.net/req/202006192/images/players/snellto01.jpg", "MAKE_MISS": "MAKE", "VALUE": 1, "DISTANCE": "15 ft", "TEAM": "home", "HOME_SCORE": 91, "VISITOR_SCORE": 85}, {"x": "25.0 ft", "y": "15.0 ft", "QUARTER": 4, "TIME_REMAINING": "3:53.0", "PLAYER": "Tony Snell", "IMAGE": "https://d2cwpp38twqe55.cloudfront.net/req/202006192/images/players/snellto01.jpg", "MAKE_MISS": "MISS", "VALUE": 1, "DISTANCE": "15 ft", "TEAM": "home", "HOME_SCORE": 91, "VISITOR_SCORE": 85}, {"QUARTER": 4, "TIME_REMAINING": "3:51.0", "PLAYER": "Nikola Miroti\u0107", "IMAGE": "https://d2cwpp38twqe55.cloudfront.net/req/202006192/images/players/mirotni01.jpg", "TEAM": "home", "HOME_SCORE": 91, "VISITOR_SCORE": 85, "REBOUND": "Offensive"}, {"QUARTER": 4, "TIME_REMAINING": "3:18.0", "PLAYER": "Nikola Miroti\u0107", "IMAGE": "https://d2cwpp38twqe55.cloudfront.net/req/202006192/images/players/mirotni01.jpg", "TEAM": "home", "HOME_SCORE": 91, "VISITOR_SCORE": 85, "REBOUND": "Defensive"}, {"x": "30.5 ft", "y": "4.08 ft", "QUARTER": 4, "TIME_REMAINING": "3:07.0", "PLAYER": "Derrick Rose", "MAKE_MISS": "MISS", "VALUE": 2, "DISTANCE": "6 ft", "TEAM": "home", "HOME_SCORE": 91, "IMAGE": "https://d2cwpp38twqe55.cloudfront.net/req/202006192/images/players/rosede01.jpg"}, {"QUARTER": 4, "TIME_REMAINING": "2:58.0", "PLAYER": "Jimmy Butler", "IMAGE": "https://d2cwpp38twqe55.cloudfront.net/req/202006192/images/players/butleji01.jpg", "TEAM": "home", "HOME_SCORE": 91, "VISITOR_SCORE": 85, "REBOUND": "Defensive"}, {"x": "15.7 ft", "y": "3.28 ft", "QUARTER": 4, "TIME_REMAINING": "2:42.0", "PLAYER": "Derrick Rose", "MAKE_MISS": "MAKE", "VALUE": 2, "DISTANCE": "8 ft", "TEAM": "home", "HOME_SCORE": 93, "IMAGE": "https://d2cwpp38twqe55.cloudfront.net/req/202006192/images/players/rosede01.jpg"}, {"x": "0.5 ft", "y": "0.89 ft", "QUARTER": 4, "TIME_REMAINING": "1:58.0", "PLAYER": "Nikola Miroti\u0107", "MAKE_MISS": "MISS", "VALUE": 3, "DISTANCE": "23 ft", "TEAM": "home", "HOME_SCORE": 93, "IMAGE": "https://d2cwpp38twqe55.cloudfront.net/req/202006192/images/players/mirotni01.jpg"}, {"x": "25.0 ft", "y": "15.0 ft", "QUARTER": 4, "TIME_REMAINING": "1:38.0", "PLAYER": "Jimmy Butler", "IMAGE": "https://d2cwpp38twqe55.cloudfront.net/req/202006192/images/players/butleji01.jpg", "MAKE_MISS": "MAKE", "VALUE": 1, "DISTANCE": "15 ft", "TEAM": "home", "HOME_SCORE": 94, "VISITOR_SCORE": 87}, {"x": "25.0 ft", "y": "15.0 ft", "QUARTER": 4, "TIME_REMAINING": "1:38.0", "PLAYER": "Jimmy Butler", "IMAGE": "https://d2cwpp38twqe55.cloudfront.net/req/202006192/images/players/butleji01.jpg", "MAKE_MISS": "MAKE", "VALUE": 1, "DISTANCE": "15 ft", "TEAM": "home", "HOME_SCORE": 95, "VISITOR_SCORE": 87}, {"x": "5.3 ft", "y": "0.89 ft", "QUARTER": 4, "TIME_REMAINING": "1:15.0", "PLAYER": "Jimmy Butler", "MAKE_MISS": "MAKE", "VALUE": 2, "DISTANCE": "18 ft", "TEAM": "home", "HOME_SCORE": 97, "ASSIST": "Derrick Rose", "IMAGE": "https://d2cwpp38twqe55.cloudfront.net/req/202006192/images/players/butleji01.jpg"}, {"x": "28.7 ft", "y": "7.06 ft", "QUARTER": 4, "TIME_REMAINING": "0:44.0", "PLAYER": "Nikola Miroti\u0107", "MAKE_MISS": "MISS", "VALUE": 2, "DISTANCE": "6 ft", "TEAM": "home", "HOME_SCORE": 97, "IMAGE": "https://d2cwpp38twqe55.cloudfront.net/req/202006192/images/players/mirotni01.jpg"}, {"x": "15.4 ft", "y": "21.2 ft", "QUARTER": 4, "TIME_REMAINING": "0:10.0", "PLAYER": "Derrick Rose", "MAKE_MISS": "MISS", "VALUE": 2, "DISTANCE": "20 ft", "TEAM": "home", "HOME_SCORE": 97, "IMAGE": "https://d2cwpp38twqe55.cloudfront.net/req/202006192/images/players/rosede01.jpg"}], "shots_visitor": [{"QUARTER": 1, "TIME_REMAINING": "11:34.0", "PLAYER": "Kevin Love", "IMAGE": "https://d2cwpp38twqe55.cloudfront.net/req/202006192/images/players/loveke01.jpg", "TEAM": "visitor", "HOME_SCORE": 0, "VISITOR_SCORE": 0, "REBOUND": "Defensive"}, {"x": "24.0 ft", "y": "3.08 ft", "QUARTER": 1, "TIME_REMAINING": "11:23.0", "PLAYER": "Kevin Love", "MAKE_MISS": "MAKE", "VALUE": 2, "DISTANCE": "0 ft", "TEAM": "visitor", "VISITOR_SCORE": 2, "ASSIST": "LeBron James"}, {"QUARTER": 1, "TIME_REMAINING": "11:09.0", "PLAYER": "Timofey Mozgov", "IMAGE": "https://d2cwpp38twqe55.cloudfront.net/req/202006192/images/players/mozgoti01.jpg", "TEAM": "visitor", "HOME_SCORE": 0, "VISITOR_SCORE": 2, "REBOUND": "Defensive"}, {"x": "6.9 ft", "y": "15.8 ft", "QUARTER": 1, "TIME_REMAINING": "11:03.0", "PLAYER": "Mo Williams", "MAKE_MISS": "MAKE", "VALUE": 2, "DISTANCE": "21 ft", "TEAM": "visitor", "IMAGE": "https://image.shutterstock.com/image-illustration/3d-small-person-double-thumbs-260nw-92842738.jpg", "VISITOR_SCORE": 4}, {"QUARTER": 1, "TIME_REMAINING": "10:47.0", "PLAYER": "LeBron James", "IMAGE": "https://d2cwpp38twqe55.cloudfront.net/req/202006192/images/players/jamesle01.jpg", "TEAM": "visitor", "HOME_SCORE": 0, "VISITOR_SCORE": 4, "REBOUND": "Defensive"}, {"x": "4.9 ft", "y": "9.45 ft", "QUARTER": 1, "TIME_REMAINING": "10:28.0", "PLAYER": "LeBron James", "MAKE_MISS": "MAKE", "VALUE": 2, "DISTANCE": "20 ft", "TEAM": "visitor", "IMAGE": "https://d2cwpp38twqe55.cloudfront.net/req/202006192/images/players/jamesle01.jpg", "VISITOR_SCORE": 6}, {"x": "25.9 ft", "y": "24.2 ft", "QUARTER": 1, "TIME_REMAINING": "9:47.0", "PLAYER": "LeBron James", "MAKE_MISS": "MISS", "VALUE": 2, "DISTANCE": "21 ft", "TEAM": "visitor", "IMAGE": "https://d2cwpp38twqe55.cloudfront.net/req/202006192/images/players/jamesle01.jpg", "VISITOR_SCORE": 6}, {"x": "21.3 ft", "y": "9.45 ft", "QUARTER": 1, "TIME_REMAINING": "9:16.0", "PLAYER": "LeBron James", "MAKE_MISS": "MISS", "VALUE": 2, "DISTANCE": "7 ft", "TEAM": "visitor", "VISITOR_SCORE": 6}, {"x": "23.3 ft", "y": "5.07 ft", "QUARTER": 1, "TIME_REMAINING": "9:15.0", "PLAYER": "Timofey Mozgov", "MAKE_MISS": "MAKE", "VALUE": 2, "DISTANCE": "2 ft", "TEAM": "visitor", "IMAGE": "https://d2cwpp38twqe55.cloudfront.net/req/202006192/images/players/mozgoti01.jpg", "VISITOR_SCORE": 8}, {"QUARTER": 1, "TIME_REMAINING": "9:15.0", "PLAYER": "Timofey Mozgov", "IMAGE": "https://d2cwpp38twqe55.cloudfront.net/req/202006192/images/players/mozgoti01.jpg", "TEAM": "visitor", "HOME_SCORE": 4, "VISITOR_SCORE": 6, "REBOUND": "Offensive"}, {"QUARTER": 1, "TIME_REMAINING": "9:05.0", "PLAYER": "Mo Williams", "IMAGE": "https://image.shutterstock.com/image-illustration/3d-small-person-double-thumbs-260nw-92842738.jpg", "TEAM": "visitor", "HOME_SCORE": 4, "VISITOR_SCORE": 8, "REBOUND": "Defensive"}, {"x": "24.0 ft", "y": "3.08 ft", "QUARTER": 1, "TIME_REMAINING": "9:02.0", "PLAYER": "LeBron James", "MAKE_MISS": "MAKE", "VALUE": 2, "DISTANCE": "0 ft", "TEAM": "visitor", "IMAGE": "https://d2cwpp38twqe55.cloudfront.net/req/202006192/images/players/jamesle01.jpg", "VISITOR_SCORE": 10, "ASSIST": "Mo Williams"}, {"QUARTER": 1, "TIME_REMAINING": "8:39.0", "PLAYER": "Kevin Love", "IMAGE": "https://d2cwpp38twqe55.cloudfront.net/req/202006192/images/players/loveke01.jpg", "TEAM": "visitor", "HOME_SCORE": 4, "VISITOR_SCORE": 10, "REBOUND": "Defensive"}, {"x": "26.4 ft", "y": "5.07 ft", "QUARTER": 1, "TIME_REMAINING": "8:31.0", "PLAYER": "Kevin Love", "MAKE_MISS": "MISS", "VALUE": 2, "DISTANCE": "3 ft", "TEAM": "visitor", "IMAGE": "https://d2cwpp38twqe55.cloudfront.net/req/202006192/images/players/loveke01.jpg", "VISITOR_SCORE": 10}, {"QUARTER": 1, "TIME_REMAINING": "8:29.0", "PLAYER": "Timofey Mozgov", "IMAGE": "https://d2cwpp38twqe55.cloudfront.net/req/202006192/images/players/mozgoti01.jpg", "TEAM": "visitor", "HOME_SCORE": 4, "VISITOR_SCORE": 10, "REBOUND": "Offensive"}, {"x": "21.0 ft", "y": "4.28 ft", "QUARTER": 1, "TIME_REMAINING": "8:27.0", "PLAYER": "Timofey Mozgov", "MAKE_MISS": "MISS", "VALUE": 2, "DISTANCE": "3 ft", "TEAM": "visitor", "IMAGE": "https://d2cwpp38twqe55.cloudfront.net/req/202006192/images/players/mozgoti01.jpg", "VISITOR_SCORE": 10}, {"x": "24.0 ft", "y": "4.58 ft", "QUARTER": 1, "TIME_REMAINING": "8:26.0", "PLAYER": "Kevin Love", "MAKE_MISS": "MISS", "VALUE": 2, "DISTANCE": "1 ft", "TEAM": "visitor", "VISITOR_SCORE": 10, "IMAGE": "https://d2cwpp38twqe55.cloudfront.net/req/202006192/images/players/loveke01.jpg"}, {"QUARTER": 1, "TIME_REMAINING": "8:26.0", "PLAYER": "Kevin Love", "IMAGE": "https://d2cwpp38twqe55.cloudfront.net/req/202006192/images/players/loveke01.jpg", "TEAM": "visitor", "HOME_SCORE": 4, "VISITOR_SCORE": 10, "REBOUND": "Offensive"}, {"x": "25.9 ft", "y": "5.07 ft", "QUARTER": 1, "TIME_REMAINING": "7:57.0", "PLAYER": "LeBron James", "MAKE_MISS": "MAKE", "VALUE": 2, "DISTANCE": "2 ft", "TEAM": "visitor", "VISITOR_SCORE": 12, "ASSIST": "Kevin Love"}, {"QUARTER": 1, "TIME_REMAINING": "7:37.0", "PLAYER": "LeBron James", "IMAGE": "https://d2cwpp38twqe55.cloudfront.net/req/202006192/images/players/jamesle01.jpg", "TEAM": "visitor", "HOME_SCORE": 6, "VISITOR_SCORE": 12, "REBOUND": "Defensive"}, {"QUARTER": 1, "TIME_REMAINING": "7:18.0", "PLAYER": "LeBron James", "IMAGE": "https://d2cwpp38twqe55.cloudfront.net/req/202006192/images/players/jamesle01.jpg", "TEAM": "visitor", "HOME_SCORE": 6, "VISITOR_SCORE": 12, "REBOUND": "Defensive"}, {"x": "35.4 ft", "y": "25.6 ft", "QUARTER": 1, "TIME_REMAINING": "7:10.0", "PLAYER": "Mo Williams", "MAKE_MISS": "MISS", "VALUE": 3, "DISTANCE": "25 ft", "TEAM": "visitor", "VISITOR_SCORE": 12}, {"QUARTER": 1, "TIME_REMAINING": "7:09.0", "PLAYER": "J.R. Smith", "IMAGE": "https://d2cwpp38twqe55.cloudfront.net/req/202006192/images/players/smithjr01.jpg", "TEAM": "visitor", "HOME_SCORE": 6, "VISITOR_SCORE": 12, "REBOUND": "Offensive"}, {"x": "13.4 ft", "y": "27.2 ft", "QUARTER": 1, "TIME_REMAINING": "6:47.0", "PLAYER": "J.R. Smith", "MAKE_MISS": "MISS", "VALUE": 3, "DISTANCE": "26 ft", "TEAM": "visitor", "IMAGE": "https://d2cwpp38twqe55.cloudfront.net/req/202006192/images/players/smithjr01.jpg", "VISITOR_SCORE": 12}, {"x": "9.3 ft", "y": "23.2 ft", "QUARTER": 1, "TIME_REMAINING": "6:16.0", "PLAYER": "Richard Jefferson", "MAKE_MISS": "MAKE", "VALUE": 3, "DISTANCE": "25 ft", "TEAM": "visitor", "VISITOR_SCORE": 15, "ASSIST": "Mo Williams", "IMAGE": "https://d2cwpp38twqe55.cloudfront.net/req/202006192/images/players/jefferi01.jpg"}, {"x": "20.3 ft", "y": "4.08 ft", "QUARTER": 1, "TIME_REMAINING": "5:41.0", "PLAYER": "Timofey Mozgov", "MAKE_MISS": "MISS", "VALUE": 2, "DISTANCE": "3 ft", "TEAM": "visitor", "VISITOR_SCORE": 15, "IMAGE": "https://d2cwpp38twqe55.cloudfront.net/req/202006192/images/players/mozgoti01.jpg"}, {"x": "6.1 ft", "y": "19.3 ft", "QUARTER": 1, "TIME_REMAINING": "5:32.0", "PLAYER": "Kevin Love", "MAKE_MISS": "MISS", "VALUE": 3, "DISTANCE": "24 ft", "TEAM": "visitor", "VISITOR_SCORE": 15, "IMAGE": "https://d2cwpp38twqe55.cloudfront.net/req/202006192/images/players/loveke01.jpg"}, {"QUARTER": 1, "TIME_REMAINING": "5:10.0", "PLAYER": "Mo Williams", "IMAGE": "https://image.shutterstock.com/image-illustration/3d-small-person-double-thumbs-260nw-92842738.jpg", "TEAM": "visitor", "HOME_SCORE": 12, "VISITOR_SCORE": 15, "REBOUND": "Defensive"}, {"x": "4.39 ft", "y": "13.4 ft", "QUARTER": 1, "TIME_REMAINING": "5:04.0", "PLAYER": "Mo Williams", "MAKE_MISS": "MISS", "VALUE": 2, "DISTANCE": "22 ft", "TEAM": "visitor", "VISITOR_SCORE": 15, "IMAGE": "https://image.shutterstock.com/image-illustration/3d-small-person-double-thumbs-260nw-92842738.jpg"}, {"x": "23.5 ft", "y": "16.0 ft", "QUARTER": 1, "TIME_REMAINING": "4:37.0", "PLAYER": "Tristan Thompson", "MAKE_MISS": "MISS", "VALUE": 2, "DISTANCE": "13 ft", "TEAM": "visitor", "VISITOR_SCORE": 15, "IMAGE": "https://d2cwpp38twqe55.cloudfront.net/req/202006192/images/players/thomptr01.jpg"}, {"x": "23.5 ft", "y": "2.98 ft", "QUARTER": 1, "TIME_REMAINING": "4:37.0", "PLAYER": "Kevin Love", "MAKE_MISS": "MISS", "VALUE": 2, "DISTANCE": "0 ft", "TEAM": "visitor", "IMAGE": "https://d2cwpp38twqe55.cloudfront.net/req/202006192/images/players/loveke01.jpg"}, {"QUARTER": 1, "TIME_REMAINING": "4:37.0", "PLAYER": "Kevin Love", "IMAGE": "https://d2cwpp38twqe55.cloudfront.net/req/202006192/images/players/loveke01.jpg", "TEAM": "visitor", "HOME_SCORE": 15, "VISITOR_SCORE": 15, "REBOUND": "Offensive"}, {"x": "32.7 ft", "y": "9.95 ft", "QUARTER": 1, "TIME_REMAINING": "3:54.0", "PLAYER": "Matthew Dellavedova", "MAKE_MISS": "MISS", "VALUE": 2, "DISTANCE": "11 ft", "TEAM": "visitor", "VISITOR_SCORE": 15}, {"QUARTER": 1, "TIME_REMAINING": "3:34.0", "PLAYER": "Tristan Thompson", "IMAGE": "https://d2cwpp38twqe55.cloudfront.net/req/202006192/images/players/thomptr01.jpg", "TEAM": "visitor", "HOME_SCORE": 17, "VISITOR_SCORE": 15, "REBOUND": "Defensive"}, {"x": "8.5 ft", "y": "2.98 ft", "QUARTER": 1, "TIME_REMAINING": "3:20.0", "PLAYER": "Tristan Thompson", "MAKE_MISS": "MISS", "VALUE": 2, "DISTANCE": "15 ft", "TEAM": "visitor", "VISITOR_SCORE": 15, "IMAGE": "https://d2cwpp38twqe55.cloudfront.net/req/202006192/images/players/thomptr01.jpg"}, {"QUARTER": 1, "TIME_REMAINING": "2:55.0", "PLAYER": "LeBron James", "IMAGE": "https://d2cwpp38twqe55.cloudfront.net/req/202006192/images/players/jamesle01.jpg", "TEAM": "visitor", "HOME_SCORE": 17, "VISITOR_SCORE": 15, "REBOUND": "Defensive"}, {"x": "14.7 ft", "y": "24.1 ft", "QUARTER": 1, "TIME_REMAINING": "2:42.0", "PLAYER": "LeBron James", "MAKE_MISS": "MISS", "VALUE": 2, "DISTANCE": "23 ft", "TEAM": "visitor", "VISITOR_SCORE": 15, "IMAGE": "https://d2cwpp38twqe55.cloudfront.net/req/202006192/images/players/jamesle01.jpg"}, {"x": "33.2 ft", "y": "25.1 ft", "QUARTER": 1, "TIME_REMAINING": "1:59.0", "PLAYER": "James Jones", "MAKE_MISS": "MISS", "VALUE": 3, "DISTANCE": "24 ft", "TEAM": "visitor", "VISITOR_SCORE": 15, "IMAGE": "https://d2cwpp38twqe55.cloudfront.net/req/202006192/images/players/jonesja02.jpg"}, {"x": "3.1 ft", "y": "17.0 ft", "QUARTER": 1, "TIME_REMAINING": "1:47.0", "PLAYER": "James Jones", "MAKE_MISS": "MISS", "VALUE": 3, "DISTANCE": "25 ft", "TEAM": "visitor", "VISITOR_SCORE": 15}, {"x": "26.2 ft", "y": "3.68 ft", "QUARTER": 1, "TIME_REMAINING": "1:20.0", "PLAYER": "LeBron James", "MAKE_MISS": "MAKE", "VALUE": 2, "DISTANCE": "2 ft", "TEAM": "visitor", "VISITOR_SCORE": 17, "ASSIST": "Matthew Dellavedova", "IMAGE": "https://d2cwpp38twqe55.cloudfront.net/req/202006192/images/players/jamesle01.jpg"}, {"x": "24.0 ft", "y": "3.08 ft", "QUARTER": 1, "TIME_REMAINING": "0:32.0", "PLAYER": "Jared Cunningham", "MAKE_MISS": "MISS", "VALUE": 2, "DISTANCE": "0 ft", "TEAM": "visitor", "VISITOR_SCORE": 17, "IMAGE": "https://d2cwpp38twqe55.cloudfront.net/req/202006192/images/players/cunnija01.jpg"}, {"x": "6.60 ft", "y": "5.27 ft", "QUARTER": 1, "TIME_REMAINING": "0:00.0", "PLAYER": "Tristan Thompson", "MAKE_MISS": "MISS", "VALUE": 2, "DISTANCE": "17 ft", "TEAM": "visitor", "VISITOR_SCORE": 17, "IMAGE": "https://d2cwpp38twqe55.cloudfront.net/req/202006192/images/players/thomptr01.jpg"}, {"x": "11.7 ft", "y": "22.4 ft", "QUARTER": 2, "TIME_REMAINING": "11:41.0", "PLAYER": "Jared Cunningham", "MAKE_MISS": "MISS", "VALUE": 2, "DISTANCE": "23 ft", "TEAM": "visitor", "VISITOR_SCORE": 17}, {"x": "10.7 ft", "y": "25.1 ft", "QUARTER": 2, "TIME_REMAINING": "11:02.0", "PLAYER": "Mo Williams", "MAKE_MISS": "MAKE", "VALUE": 3, "DISTANCE": "25 ft", "TEAM": "visitor", "VISITOR_SCORE": 20, "ASSIST": "J.R. Smith", "IMAGE": "https://image.shutterstock.com/image-illustration/3d-small-person-double-thumbs-260nw-92842738.jpg"}, {"x": "21.6 ft", "y": "3.68 ft", "QUARTER": 2, "TIME_REMAINING": "10:21.0", "PLAYER": "Mo Williams", "MAKE_MISS": "MAKE", "VALUE": 2, "DISTANCE": "2 ft", "TEAM": "visitor", "VISITOR_SCORE": 22, "ASSIST": "LeBron James"}, {"QUARTER": 2, "TIME_REMAINING": "10:08.0", "PLAYER": "Timofey Mozgov", "IMAGE": "https://d2cwpp38twqe55.cloudfront.net/req/202006192/images/players/mozgoti01.jpg", "TEAM": "visitor", "HOME_SCORE": 30, "VISITOR_SCORE": 22, "REBOUND": "Defensive"}, {"x": "25.0 ft", "y": "15.0 ft", "QUARTER": 2, "TIME_REMAINING": "10:06.0", "PLAYER": "LeBron James", "IMAGE": "https://d2cwpp38twqe55.cloudfront.net/req/202006192/images/players/jamesle01.jpg", "MAKE_MISS": "MISS", "VALUE": 1, "DISTANCE": "15 ft", "TEAM": "visitor", "HOME_SCORE": 30, "VISITOR_SCORE": 22}, {"x": "25.0 ft", "y": "15.0 ft", "QUARTER": 2, "TIME_REMAINING": "10:06.0", "PLAYER": "LeBron James", "IMAGE": "https://d2cwpp38twqe55.cloudfront.net/req/202006192/images/players/jamesle01.jpg", "MAKE_MISS": "MISS", "VALUE": 1, "DISTANCE": "15 ft", "TEAM": "visitor", "HOME_SCORE": 30, "VISITOR_SCORE": 22}, {"QUARTER": 2, "TIME_REMAINING": "9:51.0", "PLAYER": "LeBron James", "IMAGE": "https://d2cwpp38twqe55.cloudfront.net/req/202006192/images/players/jamesle01.jpg", "TEAM": "visitor", "HOME_SCORE": 30, "VISITOR_SCORE": 22, "REBOUND": "Defensive"}, {"x": "21.8 ft", "y": "4.28 ft", "QUARTER": 2, "TIME_REMAINING": "9:48.0", "PLAYER": "LeBron James", "MAKE_MISS": "MISS", "VALUE": 2, "DISTANCE": "2 ft", "TEAM": "visitor", "VISITOR_SCORE": 22, "IMAGE": "https://d2cwpp38twqe55.cloudfront.net/req/202006192/images/players/jamesle01.jpg"}, {"x": "23.9 ft", "y": "8.06 ft", "QUARTER": 2, "TIME_REMAINING": "9:18.0", "PLAYER": "Timofey Mozgov", "MAKE_MISS": "MISS", "VALUE": 2, "DISTANCE": "5 ft", "TEAM": "visitor", "VISITOR_SCORE": 22, "IMAGE": "https://d2cwpp38twqe55.cloudfront.net/req/202006192/images/players/mozgoti01.jpg"}, {"x": "26.5 ft", "y": "4.58 ft", "QUARTER": 2, "TIME_REMAINING": "9:02.0", "PLAYER": "Kevin Love", "MAKE_MISS": "MISS", "VALUE": 2, "DISTANCE": "2 ft", "TEAM": "visitor", "VISITOR_SCORE": 22}, {"QUARTER": 2, "TIME_REMAINING": "8:44.0", "PLAYER": "LeBron James", "IMAGE": "https://d2cwpp38twqe55.cloudfront.net/req/202006192/images/players/jamesle01.jpg", "TEAM": "visitor", "HOME_SCORE": 32, "VISITOR_SCORE": 22, "REBOUND": "Defensive"}, {"x": "35.5 ft", "y": "24.6 ft", "QUARTER": 2, "TIME_REMAINING": "8:36.0", "PLAYER": "LeBron James", "MAKE_MISS": "MISS", "VALUE": 3, "DISTANCE": "24 ft", "TEAM": "visitor", "VISITOR_SCORE": 22}, {"QUARTER": 2, "TIME_REMAINING": "8:35.0", "PLAYER": "Kevin Love", "IMAGE": "https://d2cwpp38twqe55.cloudfront.net/req/202006192/images/players/loveke01.jpg", "TEAM": "visitor", "HOME_SCORE": 32, "VISITOR_SCORE": 22, "REBOUND": "Offensive"}, {"x": "22.8 ft", "y": "5.07 ft", "QUARTER": 2, "TIME_REMAINING": "8:26.0", "PLAYER": "LeBron James", "MAKE_MISS": "MISS", "VALUE": 2, "DISTANCE": "2 ft", "TEAM": "visitor", "VISITOR_SCORE": 22, "IMAGE": "https://d2cwpp38twqe55.cloudfront.net/req/202006192/images/players/jamesle01.jpg"}, {"QUARTER": 2, "TIME_REMAINING": "8:17.0", "PLAYER": "J.R. Smith", "IMAGE": "https://d2cwpp38twqe55.cloudfront.net/req/202006192/images/players/smithjr01.jpg", "TEAM": "visitor", "HOME_SCORE": 32, "VISITOR_SCORE": 22, "REBOUND": "Defensive"}, {"x": "25.0 ft", "y": "15.0 ft", "QUARTER": 2, "TIME_REMAINING": "8:09.0", "PLAYER": "Timofey Mozgov", "IMAGE": "https://d2cwpp38twqe55.cloudfront.net/req/202006192/images/players/mozgoti01.jpg", "MAKE_MISS": "MISS", "VALUE": 1, "DISTANCE": "15 ft", "TEAM": "visitor", "HOME_SCORE": 32, "VISITOR_SCORE": 22}, {"x": "25.0 ft", "y": "15.0 ft", "QUARTER": 2, "TIME_REMAINING": "8:09.0", "PLAYER": "Timofey Mozgov", "IMAGE": "https://d2cwpp38twqe55.cloudfront.net/req/202006192/images/players/mozgoti01.jpg", "MAKE_MISS": "MAKE", "VALUE": 1, "DISTANCE": "15 ft", "TEAM": "visitor", "HOME_SCORE": 32, "VISITOR_SCORE": 23}, {"x": "14.3 ft", "y": "12.6 ft", "QUARTER": 2, "TIME_REMAINING": "7:27.0", "PLAYER": "J.R. Smith", "MAKE_MISS": "MISS", "VALUE": 2, "DISTANCE": "13 ft", "TEAM": "visitor", "VISITOR_SCORE": 23, "IMAGE": "https://d2cwpp38twqe55.cloudfront.net/req/202006192/images/players/smithjr01.jpg"}, {"x": "24.4 ft", "y": "4.28 ft", "QUARTER": 2, "TIME_REMAINING": "7:08.0", "PLAYER": "LeBron James", "MAKE_MISS": "MAKE", "VALUE": 2, "DISTANCE": "1 ft", "TEAM": "visitor", "VISITOR_SCORE": 25, "ASSIST": "Mo Williams", "IMAGE": "https://d2cwpp38twqe55.cloudfront.net/req/202006192/images/players/jamesle01.jpg"}, {"QUARTER": 2, "TIME_REMAINING": "6:39.0", "PLAYER": "Kevin Love", "IMAGE": "https://d2cwpp38twqe55.cloudfront.net/req/202006192/images/players/loveke01.jpg", "TEAM": "visitor", "HOME_SCORE": 34, "VISITOR_SCORE": 25, "REBOUND": "Defensive"}, {"x": "25.0 ft", "y": "15.0 ft", "QUARTER": 2, "TIME_REMAINING": "6:23.0", "PLAYER": "LeBron James", "IMAGE": "https://d2cwpp38twqe55.cloudfront.net/req/202006192/images/players/jamesle01.jpg", "MAKE_MISS": "MISS", "VALUE": 1, "DISTANCE": "15 ft", "TEAM": "visitor", "HOME_SCORE": 34, "VISITOR_SCORE": 25}, {"x": "27.0 ft", "y": "5.27 ft", "QUARTER": 2, "TIME_REMAINING": "6:00.0", "PLAYER": "J.R. Smith", "MAKE_MISS": "MISS", "VALUE": 2, "DISTANCE": "3 ft", "TEAM": "visitor", "VISITOR_SCORE": 25}, {"x": "3.59 ft", "y": "2.88 ft", "QUARTER": 2, "TIME_REMAINING": "5:22.0", "PLAYER": "J.R. Smith", "MAKE_MISS": "MISS", "VALUE": 2, "DISTANCE": "20 ft", "TEAM": "visitor", "VISITOR_SCORE": 25, "IMAGE": "https://d2cwpp38twqe55.cloudfront.net/req/202006192/images/players/smithjr01.jpg"}, {"QUARTER": 2, "TIME_REMAINING": "5:21.0", "PLAYER": "Anderson Varej\u00e3o", "IMAGE": "https://d2cwpp38twqe55.cloudfront.net/req/202006192/images/players/varejan01.jpg", "TEAM": "visitor", "HOME_SCORE": 34, "VISITOR_SCORE": 25, "REBOUND": "Offensive"}, {"x": "46.8 ft", "y": "-0.5 ft", "QUARTER": 2, "TIME_REMAINING": "5:17.0", "PLAYER": "Mo Williams", "MAKE_MISS": "MAKE", "VALUE": 3, "DISTANCE": "23 ft", "TEAM": "visitor", "VISITOR_SCORE": 28, "ASSIST": "J.R. Smith"}, {"x": "6.2 ft", "y": "19.9 ft", "QUARTER": 2, "TIME_REMAINING": "4:43.0", "PLAYER": "Mo Williams", "MAKE_MISS": "MISS", "VALUE": 3, "DISTANCE": "24 ft", "TEAM": "visitor", "VISITOR_SCORE": 28, "IMAGE": "https://image.shutterstock.com/image-illustration/3d-small-person-double-thumbs-260nw-92842738.jpg"}, {"x": "25.0 ft", "y": "15.0 ft", "QUARTER": 2, "TIME_REMAINING": "4:33.0", "PLAYER": "Anderson Varej\u00e3o", "IMAGE": "https://d2cwpp38twqe55.cloudfront.net/req/202006192/images/players/varejan01.jpg", "MAKE_MISS": "MAKE", "VALUE": 1, "DISTANCE": "15 ft", "TEAM": "visitor", "HOME_SCORE": 36, "VISITOR_SCORE": 29}, {"x": "25.0 ft", "y": "15.0 ft", "QUARTER": 2, "TIME_REMAINING": "4:33.0", "PLAYER": "Anderson Varej\u00e3o", "IMAGE": "https://d2cwpp38twqe55.cloudfront.net/req/202006192/images/players/varejan01.jpg", "MAKE_MISS": "MAKE", "VALUE": 1, "DISTANCE": "15 ft", "TEAM": "visitor", "HOME_SCORE": 36, "VISITOR_SCORE": 30}, {"QUARTER": 2, "TIME_REMAINING": "4:12.0", "PLAYER": "Mo Williams", "IMAGE": "https://image.shutterstock.com/image-illustration/3d-small-person-double-thumbs-260nw-92842738.jpg", "TEAM": "visitor", "HOME_SCORE": 36, "VISITOR_SCORE": 30, "REBOUND": "Defensive"}, {"x": "8.7 ft", "y": "10.9 ft", "QUARTER": 2, "TIME_REMAINING": "3:58.0", "PLAYER": "Mo Williams", "MAKE_MISS": "MISS", "VALUE": 2, "DISTANCE": "17 ft", "TEAM": "visitor", "VISITOR_SCORE": 30, "IMAGE": "https://image.shutterstock.com/image-illustration/3d-small-person-double-thumbs-260nw-92842738.jpg"}, {"x": "25.5 ft", "y": "4.08 ft", "QUARTER": 2, "TIME_REMAINING": "3:40.0", "PLAYER": "Richard Jefferson", "MAKE_MISS": "MAKE", "VALUE": 2, "DISTANCE": "1 ft", "TEAM": "visitor", "VISITOR_SCORE": 32, "ASSIST": "Kevin Love", "IMAGE": "https://d2cwpp38twqe55.cloudfront.net/req/202006192/images/players/jefferi01.jpg"}, {"x": "25.0 ft", "y": "27.2 ft", "QUARTER": 2, "TIME_REMAINING": "3:03.0", "PLAYER": "Kevin Love", "MAKE_MISS": "MISS", "VALUE": 3, "DISTANCE": "24 ft", "TEAM": "visitor", "VISITOR_SCORE": 32, "IMAGE": "https://d2cwpp38twqe55.cloudfront.net/req/202006192/images/players/loveke01.jpg"}, {"QUARTER": 2, "TIME_REMAINING": "2:45.0", "PLAYER": "Anderson Varej\u00e3o", "IMAGE": "https://d2cwpp38twqe55.cloudfront.net/req/202006192/images/players/varejan01.jpg", "TEAM": "visitor", "HOME_SCORE": 39, "VISITOR_SCORE": 32, "REBOUND": "Defensive"}, {"x": "21.0 ft", "y": "27.0 ft", "QUARTER": 2, "TIME_REMAINING": "2:35.0", "PLAYER": "Kevin Love", "MAKE_MISS": "MAKE", "VALUE": 3, "DISTANCE": "24 ft", "TEAM": "visitor", "VISITOR_SCORE": 35, "ASSIST": "Matthew Dellavedova", "IMAGE": "https://d2cwpp38twqe55.cloudfront.net/req/202006192/images/players/loveke01.jpg"}, {"x": "6.9 ft", "y": "21.2 ft", "QUARTER": 2, "TIME_REMAINING": "1:55.0", "PLAYER": "Kevin Love", "MAKE_MISS": "MISS", "VALUE": 3, "DISTANCE": "25 ft", "TEAM": "visitor", "VISITOR_SCORE": 35, "IMAGE": "https://d2cwpp38twqe55.cloudfront.net/req/202006192/images/players/loveke01.jpg"}, {"x": "2.80 ft", "y": "2.88 ft", "QUARTER": 2, "TIME_REMAINING": "1:31.0", "PLAYER": "Matthew Dellavedova", "MAKE_MISS": "MAKE", "VALUE": 2, "DISTANCE": "21 ft", "TEAM": "visitor", "VISITOR_SCORE": 37, "ASSIST": "Richard Jefferson", "IMAGE": "https://d2cwpp38twqe55.cloudfront.net/req/202006192/images/players/dellama01.jpg"}, {"x": "24.4 ft", "y": "23.6 ft", "QUARTER": 2, "TIME_REMAINING": "1:03.0", "PLAYER": "Richard Jefferson", "MAKE_MISS": "MISS", "VALUE": 2, "DISTANCE": "20 ft", "TEAM": "visitor", "VISITOR_SCORE": 37, "IMAGE": "https://d2cwpp38twqe55.cloudfront.net/req/202006192/images/players/jefferi01.jpg"}, {"QUARTER": 2, "TIME_REMAINING": "0:52.0", "PLAYER": "Matthew Dellavedova", "IMAGE": "https://d2cwpp38twqe55.cloudfront.net/req/202006192/images/players/dellama01.jpg", "TEAM": "visitor", "HOME_SCORE": 44, "VISITOR_SCORE": 37, "REBOUND": "Defensive"}, {"x": "6.2 ft", "y": "21.7 ft", "QUARTER": 2, "TIME_REMAINING": "0:35.0", "PLAYER": "LeBron James", "MAKE_MISS": "MISS", "VALUE": 3, "DISTANCE": "25 ft", "TEAM": "visitor", "VISITOR_SCORE": 37, "IMAGE": "https://d2cwpp38twqe55.cloudfront.net/req/202006192/images/players/jamesle01.jpg"}, {"x": "13.3 ft", "y": "27.5 ft", "QUARTER": 2, "TIME_REMAINING": "0:02.0", "PLAYER": "LeBron James", "MAKE_MISS": "MAKE", "VALUE": 3, "DISTANCE": "26 ft", "TEAM": "visitor", "VISITOR_SCORE": 40, "IMAGE": "https://d2cwpp38twqe55.cloudfront.net/req/202006192/images/players/jamesle01.jpg"}, {"x": "26.0 ft", "y": "3.28 ft", "QUARTER": 3, "TIME_REMAINING": "11:38.0", "PLAYER": "LeBron James", "MAKE_MISS": "MAKE", "VALUE": 2, "DISTANCE": "2 ft", "TEAM": "visitor", "VISITOR_SCORE": 42, "IMAGE": "https://d2cwpp38twqe55.cloudfront.net/req/202006192/images/players/jamesle01.jpg"}, {"x": "25.9 ft", "y": "3.78 ft", "QUARTER": 3, "TIME_REMAINING": "10:57.0", "PLAYER": "LeBron James", "MAKE_MISS": "MAKE", "VALUE": 2, "DISTANCE": "2 ft", "TEAM": "visitor", "VISITOR_SCORE": 44, "ASSIST": "Mo Williams"}, {"x": "34.9 ft", "y": "20.7 ft", "QUARTER": 3, "TIME_REMAINING": "10:29.0", "PLAYER": "Kevin Love", "MAKE_MISS": "MAKE", "VALUE": 2, "DISTANCE": "20 ft", "TEAM": "visitor", "VISITOR_SCORE": 46, "ASSIST": "Mo Williams", "IMAGE": "https://d2cwpp38twqe55.cloudfront.net/req/202006192/images/players/loveke01.jpg"}, {"QUARTER": 3, "TIME_REMAINING": "10:10.0", "PLAYER": "J.R. Smith", "IMAGE": "https://d2cwpp38twqe55.cloudfront.net/req/202006192/images/players/smithjr01.jpg", "TEAM": "visitor", "HOME_SCORE": 53, "VISITOR_SCORE": 46, "REBOUND": "Defensive"}, {"x": "24.0 ft", "y": "3.08 ft", "QUARTER": 3, "TIME_REMAINING": "9:52.0", "PLAYER": "Timofey Mozgov", "MAKE_MISS": "MAKE", "VALUE": 2, "DISTANCE": "0 ft", "TEAM": "visitor", "VISITOR_SCORE": 48, "ASSIST": "Kevin Love"}, {"x": "26.8 ft", "y": "3.68 ft", "QUARTER": 3, "TIME_REMAINING": "9:17.0", "PLAYER": "Kevin Love", "MAKE_MISS": "MISS", "VALUE": 2, "DISTANCE": "2 ft", "TEAM": "visitor", "VISITOR_SCORE": 48}, {"QUARTER": 3, "TIME_REMAINING": "9:02.0", "PLAYER": "LeBron James", "IMAGE": "https://d2cwpp38twqe55.cloudfront.net/req/202006192/images/players/jamesle01.jpg", "TEAM": "visitor", "HOME_SCORE": 55, "VISITOR_SCORE": 48, "REBOUND": "Defensive"}, {"x": "16.4 ft", "y": "26.5 ft", "QUARTER": 3, "TIME_REMAINING": "8:55.0", "PLAYER": "J.R. Smith", "MAKE_MISS": "MISS", "VALUE": 3, "DISTANCE": "24 ft", "TEAM": "visitor", "VISITOR_SCORE": 48, "IMAGE": "https://d2cwpp38twqe55.cloudfront.net/req/202006192/images/players/smithjr01.jpg"}, {"x": "26.5 ft", "y": "5.27 ft", "QUARTER": 3, "TIME_REMAINING": "8:06.0", "PLAYER": "J.R. Smith", "MAKE_MISS": "MAKE", "VALUE": 2, "DISTANCE": "3 ft", "TEAM": "visitor", "VISITOR_SCORE": 50, "IMAGE": "https://d2cwpp38twqe55.cloudfront.net/req/202006192/images/players/smithjr01.jpg"}, {"QUARTER": 3, "TIME_REMAINING": "7:49.0", "PLAYER": "Timofey Mozgov", "IMAGE": "https://d2cwpp38twqe55.cloudfront.net/req/202006192/images/players/mozgoti01.jpg", "TEAM": "visitor", "HOME_SCORE": 61, "VISITOR_SCORE": 50, "REBOUND": "Defensive"}, {"x": "25.0 ft", "y": "15.0 ft", "QUARTER": 3, "TIME_REMAINING": "7:42.0", "PLAYER": "J.R. Smith", "IMAGE": "https://d2cwpp38twqe55.cloudfront.net/req/202006192/images/players/smithjr01.jpg", "MAKE_MISS": "MISS", "VALUE": 1, "DISTANCE": "15 ft", "TEAM": "visitor", "HOME_SCORE": 61, "VISITOR_SCORE": 50}, {"x": "25.0 ft", "y": "15.0 ft", "QUARTER": 3, "TIME_REMAINING": "7:42.0", "PLAYER": "J.R. Smith", "IMAGE": "https://d2cwpp38twqe55.cloudfront.net/req/202006192/images/players/smithjr01.jpg", "MAKE_MISS": "MISS", "VALUE": 1, "DISTANCE": "15 ft", "TEAM": "visitor", "HOME_SCORE": 61, "VISITOR_SCORE": 50}, {"QUARTER": 3, "TIME_REMAINING": "7:26.0", "PLAYER": "LeBron James", "IMAGE": "https://d2cwpp38twqe55.cloudfront.net/req/202006192/images/players/jamesle01.jpg", "TEAM": "visitor", "HOME_SCORE": 61, "VISITOR_SCORE": 50, "REBOUND": "Defensive"}, {"x": "28.2 ft", "y": "7.66 ft", "QUARTER": 3, "TIME_REMAINING": "6:28.0", "PLAYER": "J.R. Smith", "MAKE_MISS": "MAKE", "VALUE": 2, "DISTANCE": "6 ft", "TEAM": "visitor", "VISITOR_SCORE": 52, "IMAGE": "https://d2cwpp38twqe55.cloudfront.net/req/202006192/images/players/smithjr01.jpg"}, {"x": "24.4 ft", "y": "10.4 ft", "QUARTER": 3, "TIME_REMAINING": "6:01.0", "PLAYER": "Mo Williams", "MAKE_MISS": "MISS", "VALUE": 2, "DISTANCE": "7 ft", "TEAM": "visitor", "VISITOR_SCORE": 52}, {"QUARTER": 3, "TIME_REMAINING": "5:49.0", "PLAYER": "LeBron James", "IMAGE": "https://d2cwpp38twqe55.cloudfront.net/req/202006192/images/players/jamesle01.jpg", "TEAM": "visitor", "HOME_SCORE": 63, "VISITOR_SCORE": 52, "REBOUND": "Defensive"}, {"x": "26.5 ft", "y": "3.68 ft", "QUARTER": 3, "TIME_REMAINING": "5:38.0", "PLAYER": "Kevin Love", "MAKE_MISS": "MAKE", "VALUE": 2, "DISTANCE": "2 ft", "TEAM": "visitor", "VISITOR_SCORE": 54, "ASSIST": "Timofey Mozgov", "IMAGE": "https://d2cwpp38twqe55.cloudfront.net/req/202006192/images/players/loveke01.jpg"}, {"x": "25.0 ft", "y": "15.0 ft", "QUARTER": 3, "TIME_REMAINING": "5:38.0", "PLAYER": "Kevin Love", "IMAGE": "https://d2cwpp38twqe55.cloudfront.net/req/202006192/images/players/loveke01.jpg", "MAKE_MISS": "MAKE", "VALUE": 1, "DISTANCE": "15 ft", "TEAM": "visitor", "HOME_SCORE": 63, "VISITOR_SCORE": 55}, {"QUARTER": 3, "TIME_REMAINING": "5:17.0", "PLAYER": "Tristan Thompson", "IMAGE": "https://d2cwpp38twqe55.cloudfront.net/req/202006192/images/players/thomptr01.jpg", "TEAM": "visitor", "HOME_SCORE": 63, "VISITOR_SCORE": 55, "REBOUND": "Defensive"}, {"x": "22.6 ft", "y": "28.5 ft", "QUARTER": 3, "TIME_REMAINING": "5:07.0", "PLAYER": "Matthew Dellavedova", "MAKE_MISS": "MISS", "VALUE": 3, "DISTANCE": "25 ft", "TEAM": "visitor", "VISITOR_SCORE": 55, "IMAGE": "https://d2cwpp38twqe55.cloudfront.net/req/202006192/images/players/dellama01.jpg"}, {"x": "28.7 ft", "y": "12.9 ft", "QUARTER": 3, "TIME_REMAINING": "4:44.0", "PLAYER": "J.R. Smith", "MAKE_MISS": "MISS", "VALUE": 2, "DISTANCE": "11 ft", "TEAM": "visitor", "VISITOR_SCORE": 55, "IMAGE": "https://d2cwpp38twqe55.cloudfront.net/req/202006192/images/players/smithjr01.jpg"}, {"x": "34.6 ft", "y": "4.58 ft", "QUARTER": 3, "TIME_REMAINING": "4:21.0", "PLAYER": "Matthew Dellavedova", "MAKE_MISS": "MAKE", "VALUE": 2, "DISTANCE": "10 ft", "TEAM": "visitor", "VISITOR_SCORE": 57, "ASSIST": "Timofey Mozgov", "IMAGE": "https://d2cwpp38twqe55.cloudfront.net/req/202006192/images/players/dellama01.jpg"}, {"x": "32.2 ft", "y": "16.3 ft", "QUARTER": 3, "TIME_REMAINING": "3:46.0", "PLAYER": "Timofey Mozgov", "MAKE_MISS": "MISS", "VALUE": 2, "DISTANCE": "15 ft", "TEAM": "visitor", "VISITOR_SCORE": 57, "IMAGE": "https://d2cwpp38twqe55.cloudfront.net/req/202006192/images/players/mozgoti01.jpg"}, {"QUARTER": 3, "TIME_REMAINING": "3:34.0", "PLAYER": "J.R. Smith", "IMAGE": "https://d2cwpp38twqe55.cloudfront.net/req/202006192/images/players/smithjr01.jpg", "TEAM": "visitor", "HOME_SCORE": 67, "VISITOR_SCORE": 57, "REBOUND": "Defensive"}, {"x": "8.7 ft", "y": "23.2 ft", "QUARTER": 3, "TIME_REMAINING": "3:24.0", "PLAYER": "Richard Jefferson", "MAKE_MISS": "MISS", "VALUE": 3, "DISTANCE": "25 ft", "TEAM": "visitor", "VISITOR_SCORE": 57, "IMAGE": "https://d2cwpp38twqe55.cloudfront.net/req/202006192/images/players/jefferi01.jpg"}, {"x": "46.3 ft", "y": "3.18 ft", "QUARTER": 3, "TIME_REMAINING": "2:53.0", "PLAYER": "Matthew Dellavedova", "MAKE_MISS": "MISS", "VALUE": 3, "DISTANCE": "22 ft", "TEAM": "visitor", "VISITOR_SCORE": 57, "IMAGE": "https://d2cwpp38twqe55.cloudfront.net/req/202006192/images/players/dellama01.jpg"}, {"QUARTER": 3, "TIME_REMAINING": "2:52.0", "PLAYER": "Matthew Dellavedova", "IMAGE": "https://d2cwpp38twqe55.cloudfront.net/req/202006192/images/players/dellama01.jpg", "TEAM": "visitor", "HOME_SCORE": 69, "VISITOR_SCORE": 57, "REBOUND": "Offensive"}, {"x": "19.8 ft", "y": "27.2 ft", "QUARTER": 3, "TIME_REMAINING": "2:48.0", "PLAYER": "Richard Jefferson", "MAKE_MISS": "MAKE", "VALUE": 3, "DISTANCE": "24 ft", "TEAM": "visitor", "VISITOR_SCORE": 60, "ASSIST": "J.R. Smith", "IMAGE": "https://d2cwpp38twqe55.cloudfront.net/req/202006192/images/players/jefferi01.jpg"}, {"x": "26.2 ft", "y": "4.58 ft", "QUARTER": 3, "TIME_REMAINING": "2:14.0", "PLAYER": "J.R. Smith", "MAKE_MISS": "MAKE", "VALUE": 2, "DISTANCE": "2 ft", "TEAM": "visitor", "VISITOR_SCORE": 62, "ASSIST": "Matthew Dellavedova"}, {"x": "25.9 ft", "y": "3.28 ft", "QUARTER": 3, "TIME_REMAINING": "1:37.0", "PLAYER": "Richard Jefferson", "MAKE_MISS": "MAKE", "VALUE": 2, "DISTANCE": "1 ft", "TEAM": "visitor", "VISITOR_SCORE": 64, "ASSIST": "Mo Williams", "IMAGE": "https://d2cwpp38twqe55.cloudfront.net/req/202006192/images/players/jefferi01.jpg"}, {"QUARTER": 3, "TIME_REMAINING": "1:12.0", "PLAYER": "Tristan Thompson", "IMAGE": "https://d2cwpp38twqe55.cloudfront.net/req/202006192/images/players/thomptr01.jpg", "TEAM": "visitor", "HOME_SCORE": 71, "VISITOR_SCORE": 64, "REBOUND": "Defensive"}, {"x": "32.7 ft", "y": "26.0 ft", "QUARTER": 3, "TIME_REMAINING": "1:05.0", "PLAYER": "Richard Jefferson", "MAKE_MISS": "MISS", "VALUE": 3, "DISTANCE": "24 ft", "TEAM": "visitor", "VISITOR_SCORE": 64, "IMAGE": "https://d2cwpp38twqe55.cloudfront.net/req/202006192/images/players/jefferi01.jpg"}, {"QUARTER": 3, "TIME_REMAINING": "0:51.0", "PLAYER": "Tristan Thompson", "IMAGE": "https://d2cwpp38twqe55.cloudfront.net/req/202006192/images/players/thomptr01.jpg", "TEAM": "visitor", "HOME_SCORE": 71, "VISITOR_SCORE": 64, "REBOUND": "Defensive"}, {"x": "14.2 ft", "y": "19.3 ft", "QUARTER": 3, "TIME_REMAINING": "0:44.0", "PLAYER": "Mo Williams", "MAKE_MISS": "MAKE", "VALUE": 2, "DISTANCE": "19 ft", "TEAM": "visitor", "VISITOR_SCORE": 66, "IMAGE": "https://image.shutterstock.com/image-illustration/3d-small-person-double-thumbs-260nw-92842738.jpg"}, {"x": "25.0 ft", "y": "15.0 ft", "QUARTER": 3, "TIME_REMAINING": "0:21.0", "PLAYER": "Mo Williams", "IMAGE": "https://image.shutterstock.com/image-illustration/3d-small-person-double-thumbs-260nw-92842738.jpg", "MAKE_MISS": "MISS", "VALUE": 1, "DISTANCE": "15 ft", "TEAM": "visitor", "HOME_SCORE": 71, "VISITOR_SCORE": 66}, {"x": "25.0 ft", "y": "15.0 ft", "QUARTER": 3, "TIME_REMAINING": "0:21.0", "PLAYER": "Mo Williams", "IMAGE": "https://image.shutterstock.com/image-illustration/3d-small-person-double-thumbs-260nw-92842738.jpg", "MAKE_MISS": "MAKE", "VALUE": 1, "DISTANCE": "15 ft", "TEAM": "visitor", "HOME_SCORE": 71, "VISITOR_SCORE": 67}, {"x": "25.0 ft", "y": "15.0 ft", "QUARTER": 3, "TIME_REMAINING": "0:21.0", "PLAYER": "Mo Williams", "IMAGE": "https://image.shutterstock.com/image-illustration/3d-small-person-double-thumbs-260nw-92842738.jpg", "MAKE_MISS": "MAKE", "VALUE": 1, "DISTANCE": "15 ft", "TEAM": "visitor", "HOME_SCORE": 71, "VISITOR_SCORE": 68}, {"QUARTER": 4, "TIME_REMAINING": "11:35.0", "PLAYER": "Tristan Thompson", "IMAGE": "https://d2cwpp38twqe55.cloudfront.net/req/202006192/images/players/thomptr01.jpg", "TEAM": "visitor", "HOME_SCORE": 71, "VISITOR_SCORE": 68, "REBOUND": "Defensive"}, {"x": "37.3 ft", "y": "25.6 ft", "QUARTER": 4, "TIME_REMAINING": "11:30.0", "PLAYER": "Mo Williams", "MAKE_MISS": "MAKE", "VALUE": 3, "DISTANCE": "26 ft", "TEAM": "visitor", "VISITOR_SCORE": 71, "ASSIST": "Matthew Dellavedova", "IMAGE": "https://image.shutterstock.com/image-illustration/3d-small-person-double-thumbs-260nw-92842738.jpg"}, {"QUARTER": 4, "TIME_REMAINING": "11:02.0", "PLAYER": "Mo Williams", "IMAGE": "https://image.shutterstock.com/image-illustration/3d-small-person-double-thumbs-260nw-92842738.jpg", "TEAM": "visitor", "HOME_SCORE": 71, "VISITOR_SCORE": 71, "REBOUND": "Defensive"}, {"x": "0.70 ft", "y": "4.28 ft", "QUARTER": 4, "TIME_REMAINING": "10:55.0", "PLAYER": "Mo Williams", "MAKE_MISS": "MISS", "VALUE": 3, "DISTANCE": "23 ft", "TEAM": "visitor", "VISITOR_SCORE": 71}, {"QUARTER": 4, "TIME_REMAINING": "10:43.0", "PLAYER": "Tristan Thompson", "IMAGE": "https://d2cwpp38twqe55.cloudfront.net/req/202006192/images/players/thomptr01.jpg", "TEAM": "visitor", "HOME_SCORE": 71, "VISITOR_SCORE": 71, "REBOUND": "Defensive"}, {"x": "28.2 ft", "y": "9.45 ft", "QUARTER": 4, "TIME_REMAINING": "10:31.0", "PLAYER": "Matthew Dellavedova", "MAKE_MISS": "MISS", "VALUE": 2, "DISTANCE": "7 ft", "TEAM": "visitor", "VISITOR_SCORE": 71, "IMAGE": "https://d2cwpp38twqe55.cloudfront.net/req/202006192/images/players/dellama01.jpg"}, {"x": "24.0 ft", "y": "22.4 ft", "QUARTER": 4, "TIME_REMAINING": "10:01.0", "PLAYER": "Anderson Varej\u00e3o", "MAKE_MISS": "MISS", "VALUE": 2, "DISTANCE": "19 ft", "TEAM": "visitor", "VISITOR_SCORE": 71, "IMAGE": "https://d2cwpp38twqe55.cloudfront.net/req/202006192/images/players/varejan01.jpg"}, {"QUARTER": 4, "TIME_REMAINING": "9:51.0", "PLAYER": "Tristan Thompson", "IMAGE": "https://d2cwpp38twqe55.cloudfront.net/req/202006192/images/players/thomptr01.jpg", "TEAM": "visitor", "HOME_SCORE": 75, "VISITOR_SCORE": 71, "REBOUND": "Defensive"}, {"x": "0.3 ft", "y": "3.68 ft", "QUARTER": 4, "TIME_REMAINING": "9:32.0", "PLAYER": "Kevin Love", "MAKE_MISS": "MISS", "VALUE": 3, "DISTANCE": "23 ft", "TEAM": "visitor", "VISITOR_SCORE": 71, "IMAGE": "https://d2cwpp38twqe55.cloudfront.net/req/202006192/images/players/loveke01.jpg"}, {"QUARTER": 4, "TIME_REMAINING": "9:30.0", "PLAYER": "Tristan Thompson", "IMAGE": "https://d2cwpp38twqe55.cloudfront.net/req/202006192/images/players/thomptr01.jpg", "TEAM": "visitor", "HOME_SCORE": 75, "VISITOR_SCORE": 71, "REBOUND": "Offensive"}, {"QUARTER": 4, "TIME_REMAINING": "8:39.0", "PLAYER": "LeBron James", "IMAGE": "https://d2cwpp38twqe55.cloudfront.net/req/202006192/images/players/jamesle01.jpg", "TEAM": "visitor", "HOME_SCORE": 77, "VISITOR_SCORE": 71, "REBOUND": "Defensive"}, {"x": "21.8 ft", "y": "3.28 ft", "QUARTER": 4, "TIME_REMAINING": "8:32.0", "PLAYER": "LeBron James", "MAKE_MISS": "MAKE", "VALUE": 2, "DISTANCE": "2 ft", "TEAM": "visitor", "VISITOR_SCORE": 73, "IMAGE": "https://d2cwpp38twqe55.cloudfront.net/req/202006192/images/players/jamesle01.jpg"}, {"QUARTER": 4, "TIME_REMAINING": "8:09.0", "PLAYER": "Tristan Thompson", "IMAGE": "https://d2cwpp38twqe55.cloudfront.net/req/202006192/images/players/thomptr01.jpg", "TEAM": "visitor", "HOME_SCORE": 77, "VISITOR_SCORE": 73, "REBOUND": "Defensive"}, {"x": "15.7 ft", "y": "22.7 ft", "QUARTER": 4, "TIME_REMAINING": "7:59.0", "PLAYER": "LeBron James", "MAKE_MISS": "MAKE", "VALUE": 2, "DISTANCE": "21 ft", "TEAM": "visitor", "VISITOR_SCORE": 75, "IMAGE": "https://d2cwpp38twqe55.cloudfront.net/req/202006192/images/players/jamesle01.jpg"}, {"QUARTER": 4, "TIME_REMAINING": "7:47.0", "PLAYER": "J.R. Smith", "IMAGE": "https://d2cwpp38twqe55.cloudfront.net/req/202006192/images/players/smithjr01.jpg", "TEAM": "visitor", "HOME_SCORE": 77, "VISITOR_SCORE": 75, "REBOUND": "Defensive"}, {"x": "15.4 ft", "y": "26.0 ft", "QUARTER": 4, "TIME_REMAINING": "7:34.0", "PLAYER": "LeBron James", "MAKE_MISS": "MISS", "VALUE": 3, "DISTANCE": "24 ft", "TEAM": "visitor", "VISITOR_SCORE": 75, "IMAGE": "https://d2cwpp38twqe55.cloudfront.net/req/202006192/images/players/jamesle01.jpg"}, {"x": "25.0 ft", "y": "15.0 ft", "QUARTER": 4, "TIME_REMAINING": "7:18.0", "PLAYER": "J.R. Smith", "IMAGE": "https://d2cwpp38twqe55.cloudfront.net/req/202006192/images/players/smithjr01.jpg", "MAKE_MISS": "MAKE", "VALUE": 1, "DISTANCE": "15 ft", "TEAM": "visitor", "HOME_SCORE": 78, "VISITOR_SCORE": 76}, {"x": "25.0 ft", "y": "15.0 ft", "QUARTER": 4, "TIME_REMAINING": "7:18.0", "PLAYER": "J.R. Smith", "IMAGE": "https://d2cwpp38twqe55.cloudfront.net/req/202006192/images/players/smithjr01.jpg", "MAKE_MISS": "MAKE", "VALUE": 1, "DISTANCE": "15 ft", "TEAM": "visitor", "HOME_SCORE": 78, "VISITOR_SCORE": 77}, {"x": "35.0 ft", "y": "15.8 ft", "QUARTER": 4, "TIME_REMAINING": "6:42.0", "PLAYER": "Mo Williams", "MAKE_MISS": "MAKE", "VALUE": 2, "DISTANCE": "16 ft", "TEAM": "visitor", "VISITOR_SCORE": 79, "ASSIST": "Kevin Love", "IMAGE": "https://image.shutterstock.com/image-illustration/3d-small-person-double-thumbs-260nw-92842738.jpg"}, {"x": "24.0 ft", "y": "3.08 ft", "QUARTER": 4, "TIME_REMAINING": "6:01.0", "PLAYER": "Tristan Thompson", "MAKE_MISS": "MAKE", "VALUE": 2, "DISTANCE": "0 ft", "TEAM": "visitor", "VISITOR_SCORE": 81, "ASSIST": "Mo Williams", "IMAGE": "https://d2cwpp38twqe55.cloudfront.net/req/202006192/images/players/thomptr01.jpg"}, {"QUARTER": 4, "TIME_REMAINING": "5:48.0", "PLAYER": "Kevin Love", "IMAGE": "https://d2cwpp38twqe55.cloudfront.net/req/202006192/images/players/loveke01.jpg", "TEAM": "visitor", "HOME_SCORE": 82, "VISITOR_SCORE": 81, "REBOUND": "Defensive"}, {"x": "30.5 ft", "y": "3.18 ft", "QUARTER": 4, "TIME_REMAINING": "5:32.0", "PLAYER": "LeBron James", "MAKE_MISS": "MAKE", "VALUE": 2, "DISTANCE": "6 ft", "TEAM": "visitor", "VISITOR_SCORE": 83, "IMAGE": "https://d2cwpp38twqe55.cloudfront.net/req/202006192/images/players/jamesle01.jpg"}, {"x": "27.0 ft", "y": "4.28 ft", "QUARTER": 4, "TIME_REMAINING": "5:07.0", "PLAYER": "Kevin Love", "MAKE_MISS": "MISS", "VALUE": 2, "DISTANCE": "3 ft", "TEAM": "visitor", "VISITOR_SCORE": 83, "IMAGE": "https://d2cwpp38twqe55.cloudfront.net/req/202006192/images/players/loveke01.jpg"}, {"x": "23.3 ft", "y": "8.16 ft", "QUARTER": 4, "TIME_REMAINING": "4:40.0", "PLAYER": "LeBron James", "MAKE_MISS": "MAKE", "VALUE": 2, "DISTANCE": "5 ft", "TEAM": "visitor", "VISITOR_SCORE": 85, "IMAGE": "https://d2cwpp38twqe55.cloudfront.net/req/202006192/images/players/jamesle01.jpg"}, {"x": "25.9 ft", "y": "4.58 ft", "QUARTER": 4, "TIME_REMAINING": "4:00.0", "PLAYER": "J.R. Smith", "MAKE_MISS": "MISS", "VALUE": 2, "DISTANCE": "2 ft", "TEAM": "visitor", "VISITOR_SCORE": 85, "IMAGE": "https://d2cwpp38twqe55.cloudfront.net/req/202006192/images/players/smithjr01.jpg"}, {"x": "28.9 ft", "y": "3.28 ft", "QUARTER": 4, "TIME_REMAINING": "3:19.0", "PLAYER": "Mo Williams", "MAKE_MISS": "MISS", "VALUE": 2, "DISTANCE": "5 ft", "TEAM": "visitor", "VISITOR_SCORE": 85, "IMAGE": "https://image.shutterstock.com/image-illustration/3d-small-person-double-thumbs-260nw-92842738.jpg"}, {"QUARTER": 4, "TIME_REMAINING": "3:06.0", "PLAYER": "Tristan Thompson", "IMAGE": "https://d2cwpp38twqe55.cloudfront.net/req/202006192/images/players/thomptr01.jpg", "TEAM": "visitor", "HOME_SCORE": 91, "VISITOR_SCORE": 85, "REBOUND": "Defensive"}, {"x": "0.0 ft", "y": "4.08 ft", "QUARTER": 4, "TIME_REMAINING": "3:00.0", "PLAYER": "LeBron James", "MAKE_MISS": "MISS", "VALUE": 3, "DISTANCE": "24 ft", "TEAM": "visitor", "VISITOR_SCORE": 85, "IMAGE": "https://d2cwpp38twqe55.cloudfront.net/req/202006192/images/players/jamesle01.jpg"}, {"x": "27.7 ft", "y": "12.9 ft", "QUARTER": 4, "TIME_REMAINING": "2:24.0", "PLAYER": "Matthew Dellavedova", "MAKE_MISS": "MISS", "VALUE": 2, "DISTANCE": "10 ft", "TEAM": "visitor", "VISITOR_SCORE": 85}, {"x": "22.8 ft", "y": "3.38 ft", "QUARTER": 4, "TIME_REMAINING": "2:21.0", "PLAYER": "Matthew Dellavedova", "MAKE_MISS": "MAKE", "VALUE": 2, "DISTANCE": "1 ft", "TEAM": "visitor", "VISITOR_SCORE": 87, "ASSIST": "LeBron James"}, {"QUARTER": 4, "TIME_REMAINING": "1:57.0", "PLAYER": "Matthew Dellavedova", "IMAGE": "https://d2cwpp38twqe55.cloudfront.net/req/202006192/images/players/dellama01.jpg", "TEAM": "visitor", "HOME_SCORE": 93, "VISITOR_SCORE": 87, "REBOUND": "Defensive"}, {"x": "0.0 ft", "y": "2.38 ft", "QUARTER": 4, "TIME_REMAINING": "1:51.0", "PLAYER": "Mo Williams", "MAKE_MISS": "MISS", "VALUE": 3, "DISTANCE": "24 ft", "TEAM": "visitor", "VISITOR_SCORE": 87}, {"QUARTER": 4, "TIME_REMAINING": "1:50.0", "PLAYER": "Tristan Thompson", "IMAGE": "https://d2cwpp38twqe55.cloudfront.net/req/202006192/images/players/thomptr01.jpg", "TEAM": "visitor", "HOME_SCORE": 93, "VISITOR_SCORE": 87, "REBOUND": "Offensive"}, {"x": "22.6 ft", "y": "3.68 ft", "QUARTER": 4, "TIME_REMAINING": "1:31.0", "PLAYER": "Kevin Love", "MAKE_MISS": "MISS", "VALUE": 2, "DISTANCE": "1 ft", "TEAM": "visitor", "VISITOR_SCORE": 87}, {"QUARTER": 4, "TIME_REMAINING": "1:28.0", "PLAYER": "Kevin Love", "IMAGE": "https://d2cwpp38twqe55.cloudfront.net/req/202006192/images/players/loveke01.jpg", "TEAM": "visitor", "HOME_SCORE": 95, "VISITOR_SCORE": 87, "REBOUND": "Offensive"}, {"x": "25.0 ft", "y": "15.0 ft", "QUARTER": 4, "TIME_REMAINING": "1:28.0", "PLAYER": "Kevin Love", "IMAGE": "https://d2cwpp38twqe55.cloudfront.net/req/202006192/images/players/loveke01.jpg", "MAKE_MISS": "MAKE", "VALUE": 1, "DISTANCE": "15 ft", "TEAM": "visitor", "HOME_SCORE": 95, "VISITOR_SCORE": 88}, {"x": "25.0 ft", "y": "15.0 ft", "QUARTER": 4, "TIME_REMAINING": "1:28.0", "PLAYER": "Kevin Love", "IMAGE": "https://d2cwpp38twqe55.cloudfront.net/req/202006192/images/players/loveke01.jpg", "MAKE_MISS": "MAKE", "VALUE": 1, "DISTANCE": "15 ft", "TEAM": "visitor", "HOME_SCORE": 95, "VISITOR_SCORE": 89}, {"x": "47.0 ft", "y": "1.99 ft", "QUARTER": 4, "TIME_REMAINING": "1:02.0", "PLAYER": "Kevin Love", "MAKE_MISS": "MAKE", "VALUE": 3, "DISTANCE": "23 ft", "TEAM": "visitor", "VISITOR_SCORE": 92, "ASSIST": "LeBron James"}, {"QUARTER": 4, "TIME_REMAINING": "0:43.0", "PLAYER": "Matthew Dellavedova", "IMAGE": "https://d2cwpp38twqe55.cloudfront.net/req/202006192/images/players/dellama01.jpg", "TEAM": "visitor", "HOME_SCORE": 97, "VISITOR_SCORE": 92, "REBOUND": "Defensive"}, {"x": "6.7 ft", "y": "21.4 ft", "QUARTER": 4, "TIME_REMAINING": "0:33.0", "PLAYER": "Kevin Love", "MAKE_MISS": "MAKE", "VALUE": 3, "DISTANCE": "25 ft", "TEAM": "visitor", "VISITOR_SCORE": 95, "ASSIST": "LeBron James"}, {"QUARTER": 4, "TIME_REMAINING": "0:10.0", "PLAYER": "Tristan Thompson", "IMAGE": "https://d2cwpp38twqe55.cloudfront.net/req/202006192/images/players/thomptr01.jpg", "TEAM": "visitor", "HOME_SCORE": 97, "VISITOR_SCORE": 95, "REBOUND": "Defensive"}, {"x": "26.2 ft", "y": "4.08 ft", "QUARTER": 4, "TIME_REMAINING": "0:04.0", "PLAYER": "LeBron James", "MAKE_MISS": "MISS", "VALUE": 2, "DISTANCE": "2 ft", "TEAM": "visitor", "VISITOR_SCORE": 95}], "game_id": "10/27/2015_CHI_CLE"}}